Workbook
Name _dlx2: #REF!
Name _Regression_Int: 1
Name AllApps: #REF!
Name Applications: #REF!
Name IQ_CH: 110000
Name IQ_CQ: 5000
Name IQ_CY: 10000
Name IQ_DAILY: 500000
Name IQ_FH: 100000
Name IQ_FQ: 500
Name IQ_FY: 1000
Name IQ_LTM: 2000
Name IQ_MONTH: 15000
Name IQ_NTM: 6000
Name IQ_WEEK: 50000
Name IQ_YTD: 3000
Name Limit: [1]Inputs!$J$5
Name Print_Area_MI: CAPE2!$A$1547:$P$1558
Name SPWS_WBID: "D59E1A16-371E-4D0F-A93D-481B765CD67C"
Name Summ_Table: [1]Summary!$A$3:$P$127
Name Summ_Table_GD: [1]Summary!$D$3:$D$127
Name Summ_Table_Header: [1]Summary!$A$3:$P$3

Sheet Summary
A1: Group | B1: Ticker | C1: Variable | D1: Starting Date | E1: Frequency
A2: INFLATION | B2: CPILFESL | C2: Consumer Price Index for All Urban Consumers: All Items Less Food and Energy in U.S. City Average | D2: 20821 | E2: Monthly
B3: CPILFESL1YAC | C3: CPILFESL 1-Year Annualized Change (%) | D3: 21186 | E3: Monthly
B4: CPILFESL10YAC | C4: CPILFESL 10-Years Annualized Change (%) | D4: 24473 | E4: Monthly
B5: CPIAUCSL | C5: Consumer Price Index for All Urban Consumers: All Items in U.S. City Average | D5: 17168 | E5: Monthly
B6: CORESTICKM159SFRBATL | C6: Sticky Price Consumer Price Index less Food and Energy | D6: 24838 | E6: Monthly
B7: PCEPI | C7: Personal Consumption Expenditures: Chain-type Price Index | D7: 21551 | E7: Monthly
B8: PCEPILFE | C8: Personal Consumption Expenditures Excluding Food and Energy (Chain-Type Price Index) | D8: 21551 | E8: Monthly
B9: MEDCPIM158SFRBCLE | C9: Median Consumer Price Index | D9: 30317 | E9: Monthly
B10: PPIACO | C10: Producer Price Index by Commodity: All Commodities | D10: 4750 | E10: Monthly
B11: PCUOMFGOMFG | C11: Producer Price Index by Industry: Total Manufacturing Industries | D11: 31017 | E11: Monthly
A12: Production & Business Activity | B12: ISRATIO | C12: Total Business: Inventories to Sales Ratio | D12: 33604 | E12: Monthly
B13: BUSINV | C13: Total Business Inventories (Millions of Dollars) | D13: 33604 | E13: Monthly
B14: TTLCONS | C14: Total Construction Spending: Total Construction in the United States (Millions of Dollars) | D14: 33970 | E14: Monthly
B15: TLMFGCONS | C15: Total Construction Spending: Manufacturing in the United States (Millions od Dollars) | D15: 37257 | E15: Monthly
B16: USSTHPI | C16: All-Transactions House Price Index for the United States | D16: 27395 | E16: Quarterly
B17: PERMIT | C17: New Privately-Owned Housing Units Authorized in Permit-Issuing Places: Total Units (Thousands of Units) | D17: 21916 | E17: Monthly
B18: INDPRO | C18: Industrial Production: Total Index | D18: 6941 | E18: Monthly
B19: TCU | C19: Capacity Utilization: Total Index | D19: 24473 | E19: Monthly
B20: IPMAN | C20: Industrial Production: Manufacturing (NAICS) | D20: 26299 | E20: Monthly
B21: MNFCTRIRSA | C21: Manufacturers: Inventories to Sales Ratio | D21: 33604 | E21: Monthly
B22: WHLSLRIRSA | C22: Merchant Wholesalers: Inventories to Sales Ratio | D22: 33604 | E22: Monthly
B23: USSLIND | C23: Leading Index for the United States (%) | D23: 29952 | E23: Monthly
B24: USPHCI | C24: Coincident Economic Activity Index for the United States | D24: 28856 | E24: Monthly
... B26: GDPC1 | C26: Real Gross Domestic Product (Billions of Chained 2017 Dollars) | D26: 17168 | E26: Quarterly
A27: Financial Conditions | B27: NFCIRISK | C27: Chicago Fed National Financial Conditions Risk Subindex | D27: 25934 | E27: Monthly
B28: NFCICREDIT | C28: Chicago Fed National Financial Conditions Credit Subindex | D28: 25934 | E28: Monthly
B29: NFCILEVERAGE | C29: Chicago Fed National Financial Conditions Leverage Subindex | D29: 25934 | E29: Monthly
A30: Monetary Policies | B30: DFF | C30: Federal Funds Effective Rate (%) | D30: 19906 | E30: Monthly
B31: M1REAL | C31: Real M1 Money Stock (Billions of 1982-84 Dollars) | D31: 21551 | E31: Monthly
B32: M2REAL | C32: Real M2 Money Stock (Billions of 1982-84 Dollars) | D32: 21551 | E32: Monthly
B33: T10YFF | C33: 10-Year Treasury Constant Maturity Minus Federal Funds Rate (%) | D33: 22647 | E33: Monthly
A34: Equity Earning Yield | B34: CAPE | C34: Cyclically Adjusted PE Ratio | D34: 1 | E34: Monthly
A35: Labor | B35: ICSA | C35: Initial Claims (Number of Claims) | D35: 24473 | E35: Monthly
B36: IURSA | C36: Insured Unemployment Rate (%) | D36: 25934 | E36: Monthly
B37: JTSJOL | C37: Job Openings: Total Nonfarm (Thousands) | D37: 36861 | E37: Monthly
B38: PAYEMS | C38: All Employees, Total Nonfarm (Thousands) | D38: 14246 | E38: Monthly
B39: MANEMP | C39: All Employees, Manufacturing (Thousands) | D39: 14246 | E39: Monthly
B40: UNRATE | C40: Unemployment Rate (%) | D40: 17533 | E40: Monthly
A41: National Accounts | B41: IEAXGS | C41: Exports of goods and services (Millions od Dollars) | D41: 36161 | E41: Quarterly
B42: IEAMGSN | C42: Imports of goods and service (Millions od Dollars) | D42: 36161 | E42: Quarterly
B43: GFDEGDQ188S | C43: Federal Debt: Total Public Debt as Percent of Gross Domestic Product (%) | D43: 24108 | E43: Quarterly

Sheet CPILFESL
A1: Link: | B1: Consumer Price Index for All Urban Consumers: All Items Less Food and Energy in U.S. City Average
A3: Date | B3: CPILFESL
A4: 20821 | B4: 100
A5: 20852 | B5: 100.35088
A6: 20880 | B6: 100.70175
A7: 20911 | B7: 101.05263
A8: 20941 | B8: 101.05263
A9: 20972 | B9: 101.40351
A10: 21002 | B10: 101.75439
A11: 21033 | B11: 101.75439
A12: 21064 | B12: 102.10526
A13: 21094 | B13: 102.45614
A14: 21125 | B14: 102.80702
A15: 21155 | B15: 102.80702
... A812: 45413 | B812: 1116.2807

Sheet CPILFESL1YAC
A3: Date | B3: 1-Year Annualized Change
A16: =CPILFESL!A16 -> 21186 | B16: =IFERROR((CPILFESL!B16/CPILFESL!B4)^(1/12)-1, "") -> 0.0023096175
A17: =CPILFESL!A17 -> 21217 | B17: =IFERROR((CPILFESL!B17/CPILFESL!B5)^(1/12)-1, "") -> 0.0023016349
A18: =CPILFESL!A18 -> 21245 | B18: =IFERROR((CPILFESL!B18/CPILFESL!B6)^(1/12)-1, "") -> 0.0022937237
A19: =CPILFESL!A19 -> 21276 | B19: =IFERROR((CPILFESL!B19/CPILFESL!B7)^(1/12)-1, "") -> 0.0020032432
A20: =CPILFESL!A20 -> 21306 | B20: =IFERROR((CPILFESL!B20/CPILFESL!B8)^(1/12)-1, "") -> 0.0020032432
A21: =CPILFESL!A21 -> 21337 | B21: =IFERROR((CPILFESL!B21/CPILFESL!B9)^(1/12)-1, "") -> 0.001996387
A22: =CPILFESL!A22 -> 21367 | B22: =IFERROR((CPILFESL!B22/CPILFESL!B10)^(1/12)-1, "") -> 0.0017079986
A23: =CPILFESL!A23 -> 21398 | B23: =IFERROR((CPILFESL!B23/CPILFESL!B11)^(1/12)-1, "") -> 0.0017079986
A24: =CPILFESL!A24 -> 21429 | B24: =IFERROR((CPILFESL!B24/CPILFESL!B12)^(1/12)-1, "") -> 0.0017021919
A25: =CPILFESL!A25 -> 21459 | B25: =IFERROR((CPILFESL!B25/CPILFESL!B13)^(1/12)-1, "") -> 0.001415866
A26: =CPILFESL!A26 -> 21490 | B26: =IFERROR((CPILFESL!B26/CPILFESL!B14)^(1/12)-1, "") -> 0.001411063
A27: =CPILFESL!A27 -> 21520 | B27: =IFERROR((CPILFESL!B27/CPILFESL!B15)^(1/12)-1, "") -> 0.0016906721
... A812: =CPILFESL!A812 -> 45413 | B812: =IFERROR((CPILFESL!B812/CPILFESL!B800)^(1/12)-1, "") -> 0.002799057

Sheet CPILFESL10YAC
A3: Date | B3: 10-Year Annualized Change
A124: =CPILFESL!A124 -> 24473 | B124: =IFERROR((CPILFESL!B124/CPILFESL!B4)^(1/10)-1, "") -> 0.018399376
A125: =CPILFESL!A125 -> 24504 | B125: =IFERROR((CPILFESL!B125/CPILFESL!B5)^(1/10)-1, "") -> 0.018042728
A126: =CPILFESL!A126 -> 24532 | B126: =IFERROR((CPILFESL!B126/CPILFESL!B6)^(1/10)-1, "") -> 0.01798464
A127: =CPILFESL!A127 -> 24563 | B127: =IFERROR((CPILFESL!B127/CPILFESL!B7)^(1/10)-1, "") -> 0.017926908
A128: =CPILFESL!A128 -> 24593 | B128: =IFERROR((CPILFESL!B128/CPILFESL!B8)^(1/10)-1, "") -> 0.018222433
A129: =CPILFESL!A129 -> 24624 | B129: =IFERROR((CPILFESL!B129/CPILFESL!B9)^(1/10)-1, "") -> 0.018164207
A130: =CPILFESL!A130 -> 24654 | B130: =IFERROR((CPILFESL!B130/CPILFESL!B10)^(1/10)-1, "") -> 0.018106353
A131: =CPILFESL!A131 -> 24685 | B131: =IFERROR((CPILFESL!B131/CPILFESL!B11)^(1/10)-1, "") -> 0.018691638
A132: =CPILFESL!A132 -> 24716 | B132: =IFERROR((CPILFESL!B132/CPILFESL!B12)^(1/10)-1, "") -> 0.018632451
A133: =CPILFESL!A133 -> 24746 | B133: =IFERROR((CPILFESL!B133/CPILFESL!B13)^(1/10)-1, "") -> 0.018573622
A134: =CPILFESL!A134 -> 24777 | B134: =IFERROR((CPILFESL!B134/CPILFESL!B14)^(1/10)-1, "") -> 0.018515172
A135: =CPILFESL!A135 -> 24807 | B135: =IFERROR((CPILFESL!B135/CPILFESL!B15)^(1/10)-1, "") -> 0.019092404
... A812: =CPILFESL!A812 -> 45413 | B812: =IFERROR((CPILFESL!B812/CPILFESL!B692)^(1/10)-1, "") -> 0.029651279

Sheet CPIAUCSL
A1: Link: | B1: Consumer Price Index for All Urban Consumers: All Items in U.S. City Average
A3: Date | B3: CPIAUCSL
A4: 17168 | B4: 100
A5: 17199 | B5: 100.65177
A6: 17227 | B6: 102.42086
A7: 17258 | B7: 102.42086
A8: 17288 | B8: 102.18808
A9: 17319 | B9: 102.7933
A10: 17349 | B10: 103.49162
A11: 17380 | B11: 104.28305
A12: 17411 | B12: 106.33147
A13: 17441 | B13: 106.65736
A14: 17472 | B14: 107.35568
A15: 17502 | B15: 108.9851
... A932: 45413 | B932: 1458.2169

Sheet CORESTICKM159SFRBATL
A1: Link: | B1: Sticky Price Consumer Price Index less Food and Energy
A3: Date | B3: CORESTICKM159SFRBATL
A4: 24838 | B4: 100
A5: 24869 | B5: 100.60129
A6: 24898 | B6: 113.42611
A7: 24929 | B7: 113.80028
A8: 24959 | B8: 111.94964
A9: 24990 | B9: 124.47268
A10: 25020 | B10: 130.15491
A11: 25051 | B11: 135.4544
A12: 25082 | B12: 135.49932
A13: 25112 | B13: 141.91647
A14: 25143 | B14: 147.85305
A15: 25173 | B15: 156.25862
... A680: 45413 | B680: 117.80359

Sheet PCEPI
A1: Link: | B1: Personal Consumption Expenditures: Chain-type Price Index
A3: Date | B3: PCEPI
A4: 21551 | B4: 100
A5: 21582 | B5: 100.09892
A6: 21610 | B6: 100.16486
A7: 21641 | B7: 100.3627
A8: 21671 | B8: 100.41546
A9: 21702 | B9: 100.70562
A10: 21732 | B10: 100.91664
A11: 21763 | B11: 101.06173
A12: 21794 | B12: 101.32551
A13: 21824 | B13: 101.56951
A14: 21855 | B14: 101.63545
A15: 21885 | B15: 101.75415
... A788: 45413 | B788: 811.76471

Sheet PCEPILFE
A1: Link: | B1: Personal Consumption Expenditures Excluding Food and Energy (Chain-Type Price Index)
A3: Date | B3: PCEPILFE
A4: 21551 | B4: 100
A5: 21582 | B5: 100.07741
A6: 21610 | B6: 100.19354
A7: 21641 | B7: 100.44513
A8: 21671 | B8: 100.56771
A9: 21702 | B9: 100.86446
A10: 21732 | B10: 101.10315
A11: 21763 | B11: 101.26443
A12: 21794 | B12: 101.52893
A13: 21824 | B13: 101.70312
A14: 21855 | B14: 101.8902
A15: 21885 | B15: 102.04503
... A788: 45413 | B788: 787.3363

Sheet MEDCPIM158SFRBCLE
A1: Link: | B1: Median Consumer Price Indexed
A3: Date | B3: MEDCPIM158SFRBCLE
A4: 30317 | B4: 100
A5: 30348 | B5: 98.76146
A6: 30376 | B6: 72.0341
A7: 30407 | B7: 96.27892
A8: 30437 | B8: 75.12635
A9: 30468 | B9: 48.68328
A10: 30498 | B10: 73.73555
A11: 30529 | B11: 97.65362
A12: 30560 | B12: 96.47382
A13: 30590 | B13: 93.91889
A14: 30621 | B14: 97.35612
A15: 30651 | B15: 72.32336
... A500: 45413 | B500: 60.15309

Sheet PPIACO
A1: Link: | B1: Producer Price Index by Commodity: All Commodities
A3: Date | B3: PPIACO
A4: 4750 | B4: 100
A5: 4781 | B5: 99.17355
A6: 4809 | B6: 99.17355
A7: 4840 | B7: 99.17355
A8: 4870 | B8: 98.34711
A9: 4901 | B9: 98.34711
A10: 4931 | B10: 99.17355
A11: 4962 | B11: 99.17355
A12: 4993 | B12: 100.82645
A13: 5023 | B13: 100.82645
A14: 5054 | B14: 100
A15: 5084 | B15: 98.34711
... A1340: 45413 | B1340: 2107.1984

Sheet PCUOMFGOMFG
A1: Link: | B1: Producer Price Index by Industry: Total Manufacturing Industries
A3: Date | B3: PCUOMFGOMFG
A4: 31017 | B4: 100
A5: 31048 | B5: 100
A6: 31079 | B6: 100
A7: 31107 | B7: 100
A8: 31138 | B8: 100
A9: 31168 | B9: 100
A10: 31199 | B10: 100
A11: 31229 | B11: 100
A12: 31260 | B12: 100
A13: 31291 | B13: 100
A14: 31321 | B14: 100
A15: 31352 | B15: 100
... A477: 45413 | B477: 248.953

Sheet ISRATIO
A1: Link: | B1: Total Business: Inventories to Sales Ratio
A3: Date | B3: ISRATIO
A4: 33604 | B4: 1.56
A5: 33635 | B5: 1.56
A6: 33664 | B6: 1.53
A7: 33695 | B7: 1.53
A8: 33725 | B8: 1.52
A9: 33756 | B9: 1.52
A10: 33786 | B10: 1.51
A11: 33817 | B11: 1.53
A12: 33848 | B12: 1.51
A13: 33878 | B13: 1.52
A14: 33909 | B14: 1.51
A15: 33939 | B15: 1.51
... A391: 45383 | B391: 1.37

Sheet BUSINV
A1: Link: | B1: Total Business Inventories (Millions of Dollars)
A3: Date | B3: BUSINV
A4: 33604 | B4: 808292
A5: 33635 | B5: 809600
A6: 33664 | B6: 812725
A7: 33695 | B7: 815453
A8: 33725 | B8: 815016
A9: 33756 | B9: 820447
A10: 33786 | B10: 825098
A11: 33817 | B11: 826136
A12: 33848 | B12: 827513
A13: 33878 | B13: 827914
A14: 33909 | B14: 829839
A15: 33939 | B15: 835800
... A391: 45383 | B391: 2545185

Sheet TTLCONS
A1: Link: | B1: Total Construction Spending (Millions of Dollars)
A3: Date | B3: TTLCONS
A4: 33970 | B4: 458080
A5: 34001 | B5: 462967
A6: 34029 | B6: 458399
A7: 34060 | B7: 469425
A8: 34090 | B8: 468998
A9: 34121 | B9: 480247
A10: 34151 | B10: 483571
A11: 34182 | B11: 491494
A12: 34213 | B12: 497297
A13: 34243 | B13: 492823
A14: 34274 | B14: 515934
A15: 34304 | B15: 533150
... A380: 45413 | B380: 2139792

Sheet TLMFGCONS
A1: Link: | B1: Total Construction Spending: Manufacturing in the United States (Millions of Dollars)
A3: Date | B3: TLMFGCONS
A4: 37257 | B4: 28318
A5: 37288 | B5: 25977
A6: 37316 | B6: 24998
A7: 37347 | B7: 24482
A8: 37377 | B8: 23862
A9: 37408 | B9: 23200
A10: 37438 | B10: 22090
A11: 37469 | B11: 20837
A12: 37500 | B12: 20168
A13: 37530 | B13: 20908
A14: 37561 | B14: 21004
A15: 37591 | B15: 20384
... A272: 45413 | B272: 234133

Sheet USSTHPI
A1: Link: | B1: All-Transactions House Price Index for the United States (Quarterly)
A3: Date | B3: USSTHPI
A4: 27395 | B4: 100
A5: 27485 | B5: 101.43501
A6: 27576 | B6: 102.13583
A7: 27668 | B7: 103.88787
A8: 27760 | B8: 104.90572
A9: 27851 | B9: 109.16069
A10: 27942 | B10: 111.02953
A11: 28034 | B11: 112.19756
A12: 28126 | B12: 116.01869
A13: 28216 | B13: 121.32488
A14: 28307 | B14: 124.11146
A15: 28399 | B15: 128.75021
... A200: 45292 | B200: 1108.9271

Sheet PERMIT
A1: Link: | B1: New Privately-Owned Housing Units Authorized in Permit-Issuing Places: Total Units (Thousands of Units)
A3: Date | B3: PERMIT
A4: 21916 | B4: 1092
A5: 21947 | B5: 1088
A6: 21976 | B6: 955
A7: 22007 | B7: 1016
A8: 22037 | B8: 1052
A9: 22068 | B9: 958
A10: 22098 | B10: 999
A11: 22129 | B11: 994
A12: 22160 | B12: 984
A13: 22190 | B13: 972
A14: 22221 | B14: 979
A15: 22251 | B15: 951
... A776: 45413 | B776: 1399

Sheet INDPRO
A1: Link: | B1: Industrial Production: Total Index
A3: Date | B3: INDPRO
A4: 6941 | B4: 100
A5: 6972 | B5: 95.58104
A6: 7000 | B6: 92.81868
A7: 7031 | B7: 94.47527
A8: 7061 | B8: 95.02816
A9: 7092 | B9: 101.10577
A10: 7122 | B10: 107.18338
A11: 7153 | B11: 108.83997
A12: 7184 | B12: 106.63049
A13: 7214 | B13: 105.52473
A14: 7245 | B14: 103.86813
A15: 7275 | B15: 105.52473
... A1268: 45413 | B1268: 2119.39

Sheet TCU
A1: Link: | B1: Capacity Utilization: Total Index
A3: Date | B3: TCU
A4: 24473 | B4: 100
A5: 24504 | B5: 98.41683
A6: 24532 | B6: 97.41952
A7: 24563 | B7: 97.89541
A8: 24593 | B8: 96.60634
A9: 24624 | B9: 96.163
A10: 24654 | B10: 95.51752
A11: 24685 | B11: 96.91655
A12: 24716 | B12: 96.33293
A13: 24746 | B13: 96.69125
A14: 24777 | B14: 97.6456
A15: 24807 | B15: 98.26771
... A692: 45413 | B692: 87.44426

Sheet IPMAN
A1: Link: | B1: Industrial Production: Manufacturing (NAICS)
A3: Date | B3: IPMAN
A4: 26299 | B4: 100
A5: 26330 | B5: 100.76385
A6: 26359 | B6: 101.43865
A7: 26390 | B7: 102.58791
A8: 26420 | B8: 102.77518
A9: 26451 | B9: 103.08156
A10: 26481 | B10: 103.06764
A11: 26512 | B11: 104.43311
A12: 26543 | B12: 105.18054
A13: 26573 | B13: 106.75415
A14: 26604 | B14: 108.1391
A15: 26634 | B15: 109.69518
... A632: 45413 | B632: 278.3601

Sheet MNFCTRIRSA
A1: Link: | B1: Manufacturers: Inventories to Sales Ratio
A3: Date | B3: MNFCTRIRSA
A4: 33604 | B4: 1.66
A5: 33635 | B5: 1.65
A6: 33664 | B6: 1.58
A7: 33695 | B7: 1.57
A8: 33725 | B8: 1.55
A9: 33756 | B9: 1.53
A10: 33786 | B10: 1.54
A11: 33817 | B11: 1.56
A12: 33848 | B12: 1.55
A13: 33878 | B13: 1.56
A14: 33909 | B14: 1.53
A15: 33939 | B15: 1.53
... A391: 45383 | B391: 1.45

Sheet WHLSLRIRSA
A1: Link: | B1: Merchant Wholesalers: Inventories to Sales Ratio
A3: Date | B3: WHLSLRIRSA
A4: 33604 | B4: 1.32
A5: 33635 | B5: 1.31
A6: 33664 | B6: 1.31
A7: 33695 | B7: 1.31
A8: 33725 | B8: 1.31
A9: 33756 | B9: 1.32
A10: 33786 | B10: 1.29
A11: 33817 | B11: 1.31
A12: 33848 | B12: 1.3
A13: 33878 | B13: 1.3
A14: 33909 | B14: 1.3
A15: 33939 | B15: 1.33
... A391: 45383 | B391: 1.35

Sheet USSLIND
A1: Link: | B1: Leading Index for the United States (%)
A3: Date | B3: USSLIND
A4: 29952 | B4: -0.89
A5: 29983 | B5: -0.38
A6: 30011 | B6: -0.15
A7: 30042 | B7: -0.11
A8: 30072 | B8: -0.05
A9: 30103 | B9: -0.03
A10: 30133 | B10: -0.06
A11: 30164 | B11: -0.23
A12: 30195 | B12: -0.2
A13: 30225 | B13: 0.01
A14: 30256 | B14: 0.48
A15: 30286 | B15: 0.94
... A461: 43862 | B461: 1.72

Sheet USPHCI
A1: Link: | B1: Coincident Economic Activity Index for the United States
A3: Date | B3: USPHCI
A4: 28856 | B4: 100
A5: 28887 | B5: 100.3288
A6: 28915 | B6: 100.83297
A7: 28946 | B7: 100.98641
A8: 28976 | B8: 101.46865
A9: 29007 | B9: 101.75362
A10: 29037 | B10: 102.01666
A11: 29068 | B11: 102.10434
A12: 29099 | B12: 102.32354
A13: 29129 | B13: 102.52082
A14: 29160 | B14: 102.76195
A15: 29190 | B15: 102.89347
... A548: 45413 | B548: 315.73871

Sheet JHGDPBRINDX
A1: Link: | B1: GDP-Based Recession Indicator Index (%,Quarterly)
A3: Date | B3: JHGDPBRINDX
A4: 24746 | B4: 3.8348
A5: 24838 | B5: 1.7614
A6: 24929 | B6: 1.2127
A7: 25020 | B7: 2.3009
A8: 25112 | B8: 6.3338
A9: 25204 | B9: 12.9501
A10: 25294 | B10: 20.4605
A11: 25385 | B11: 45.7028
A12: 25477 | B12: 89.2282
A13: 25569 | B13: 97.60567
A14: 25659 | B14: 91.58425
A15: 25750 | B15: 94.99551
... A228: 45200 | B228: 2

Sheet GDPC1
A1: Link: | B1: Real Gross Domestic Product, Billions of Chained 2017 Dollars (Quarterly)
A3: Date | B3: GDPC1
A4: 17168 | B4: 2182.681
A5: 17258 | B5: 2176.892
A6: 17349 | B6: 2172.432
A7: 17441 | B7: 2206.452
A8: 17533 | B8: 2239.682
A9: 17624 | B9: 2276.69
A10: 17715 | B10: 2289.77
A11: 17807 | B11: 2292.364
A12: 17899 | B12: 2260.807
A13: 17989 | B13: 2253.128
A14: 18080 | B14: 2276.424
A15: 18172 | B15: 2257.352
... A312: 45292 | B312: 22758.752

Sheet NFCIRISK
A1: Link: | B1: Chicago Fed National Financial Conditions Risk Subindex
A3: Date | B3: NFCIRISK
A4: 25934 | B4: 0.726735
A5: 25965 | B5: 0.905425
A6: 25993 | B6: 1.0690775
A7: 26024 | B7: 1.421022
A8: 26054 | B8: 1.7278425
A9: 26085 | B9: 1.4202575
A10: 26115 | B10: 1.19168
A11: 26146 | B11: 1.98678
A12: 26177 | B12: 2.4685175
A13: 26207 | B13: 1.925338
A14: 26238 | B14: 1.4772425
A15: 26268 | B15: 1.524332
... A644: 45413 | B644: -0.583542
A645: 45444 | B645: =NA() -> #N/A

Sheet NFCICREDIT
A1: Link: | B1: Chicago Fed National Financial Conditions Credit Subindex
A3: Date | B3: NFCICREDIT
A4: 25934 | B4: -1.133835
A5: 25965 | B5: -1.163
A6: 25993 | B6: -1.2430525
A7: 26024 | B7: -1.429476
A8: 26054 | B8: -1.6713475
A9: 26085 | B9: -1.8363925
A10: 26115 | B10: -1.869844
A11: 26146 | B11: -1.7267525
A12: 26177 | B12: -1.5101625
A13: 26207 | B13: -1.314048
A14: 26238 | B14: -1.2596525
A15: 26268 | B15: -1.370172
... A644: 45413 | B644: -0.059984
A645: 45444 | B645: =NA() -> #N/A

Sheet NFCILEVERAGE
A1: Link: | B1: Chicago Fed National Financial Conditions Leverage Subindex
A3: Date | B3: NFCILEVERAGE
A4: 25934 | B4: -1.9392625
A5: 25965 | B5: -2.03208
A6: 25993 | B6: -2.0838725
A7: 26024 | B7: -2.064836
A8: 26054 | B8: -1.9745675
A9: 26085 | B9: -1.8626275
A10: 26115 | B10: -1.73583
A11: 26146 | B11: -1.634975
A12: 26177 | B12: -1.587245
A13: 26207 | B13: -1.595868
A14: 26238 | B14: -1.6653825
A15: 26268 | B15: -1.749604
... A644: 45413 | B644: -0.093876
A645: 45444 | B645: =NA() -> #N/A

Sheet DFF
A1: Link: | B1: Federal Funds Effective Rate (%)
A3: Date | B3: DFF
A4: 19906 | B4: 0.79935484
A5: 19937 | B5: 1.2206452
A6: 19968 | B6: 1.0666667
A7: 19998 | B7: 0.84870968
A8: 20029 | B8: 0.83366667
A9: 20059 | B9: 1.2777419
A10: 20090 | B10: 1.3912903
A11: 20121 | B11: 1.2917857
A12: 20149 | B12: 1.3467742
A13: 20180 | B13: 1.4276667
A14: 20210 | B14: 1.4332258
A15: 20241 | B15: 1.6446667
... A843: 45444 | B843: 5.33

Sheet M1REAL
A1: Link: | B1: Real M1 Money Stock (Billions of 1982-84 Dollars)
A3: Date | B3: M1REAL
A4: 21551 | B4: 478.8
A5: 21582 | B5: 480.7
A6: 21610 | B6: 482.2
A7: 21641 | B7: 482.1
A8: 21671 | B8: 484.5
A9: 21702 | B9: 485.1
A10: 21732 | B10: 486.1
A11: 21763 | B11: 486.3
A12: 21794 | B12: 482.1
A13: 21824 | B13: 478.7
A14: 21855 | B14: 478.4
A15: 21885 | B15: 475.7
... A788: 45413 | B788: 5758.3

Sheet M2REAL
A1: Link: | B1: Real M2 Money Stock (Billions of 1982-84 Dollars)
A3: Date | B3: M2REAL
A4: 21551 | B4: 987.9
A5: 21582 | B5: 992.1
A6: 21610 | B6: 998.3
A7: 21641 | B7: 1001
A8: 21671 | B8: 1006.2
A9: 21702 | B9: 1010.3
A10: 21732 | B10: 1012.7
A11: 21763 | B11: 1015.8
A12: 21794 | B12: 1014.4
A13: 21824 | B13: 1010.2
A14: 21855 | B14: 1012.3
A15: 21885 | B15: 1012.6
... A788: 45413 | B788: 6692.8

Sheet T10YFF
A1: Link: | B1: 10-Year Treasury Constant Maturity Minus Federal Funds Rate (Percent)
A3: Date | B3: T10YFF
A4: 22647 | B4: 2.0604545
A5: 22678 | B5: 1.6505556
A6: 22706 | B6: 1.0781818
A7: 22737 | B7: 1.043
A8: 22767 | B8: 1.4418182
A9: 22798 | B9: 1.2066667
A10: 22828 | B10: 1.3238095
A11: 22859 | B11: 1.03
A12: 22890 | B12: 1.0842105
A13: 22920 | B13: 1.0154545
A14: 22951 | B14: 0.97368421
A15: 22981 | B15: 0.94894737
... A753: 45444 | B753: -1.0247368
A754: 45474 | B754: =NA() -> #N/A

Sheet CAPE
A1: Link: | B1: https://shillerdata.com/
A3: Date | B3: CAPE
A4: 1 | B4: 18.674275
A5: 32 | B5: 18.703797
A6: 61 | B6: 18.775793
A7: 92 | B7: 18.936402
A8: 122 | B8: 18.403197
A9: 153 | B9: 17.992712
A10: 183 | B10: 17.689545
A11: 214 | B11: 18.069615
A12: 245 | B12: 17.341874
A13: 275 | B13: 18.102399
A14: 306 | B14: 19.419585
A15: 336 | B15: 20.744051
... A1497: 45444 | B1497: 34.075523

Sheet CAPE2
D1: Link: | P1: https://shillerdata.com/
A2: Stock Market Data Used in "Irrational Exuberance" Princeton University Press, 2000, 2005, 2015, updated | P2: Cyclically | R2: Cyclically
A3: Robert J. Shiller | P3: Adjusted | R3: Adjusted
P4: Price | R4: Total Return Price
H5: Consumer | M5: Real | O5: Real | P5: Earnings | R5: Earnings | U5: Monthly | V5: Real
E6: S&P | H6: Price | J6: Long | M6: Total | O6: TR | P6: Ratio | R6: Ratio | T6: Excess | U6: Total | V6: Total | W6: 10 Year | X6: 10 Year | Y6: Real 10 Year
E7: Comp. | F7: Dividend | G7: Earnings | H7: Index | I7: Date | J7: Interest | K7: Real | L7: Real | M7: Return | N7: Real | O7: Scaled | P7: P/E10 or | R7: TR P/E10 or | T7: CAPE | U7: Bond | V7: Bond | W7: Annualized Stock | X7: Annualized Bonds | Y7: Excess Annualized
A9: Date-wrong | B9: Year | C9: Month | D9: Date | E9: P | F9: D | G9: E | H9: CPI | I9: Fraction | J9: Rate GS10 | K9: Price | L9: Dividend | M9: Price | N9: Earnings | O9: Earnings | P9: CAPE | R9: TR CAPE | T9: Yield | U9: Returns | V9: Returns | W9: Real Return | X9: Real Return | Y9: Returns
A10: 1871.01 | B10: =VALUE(LEFT(A10, 4)) -> 1871 | C10: 1 | D10: =DATE(B10, VALUE(C10), 1) -> 683371 | E10: 4.44 | F10: 0.26 | G10: 0.4 | H10: 12.464061 | I10: =1871+1/24 -> 1871.0417 | J10: 5.32 | K10: =E10*$H$1851/H10 -> 112.01826 | L10: =F10*$H$1851/H10 -> 6.5596276 | M10: =K10 -> 112.01826 | N10: =G10*$H$1851/H10 -> 10.091735 | O10: =N10*(M10/K10) -> 10.091735 | P10: NA | R10: NA | U10: =((J10/J11+J10/1200+((1+J11/1200)^(-119))*(1-J10/J11))) -> 1.0041769 | V10: 1 | W10: =(($M130/$M10)^(1/10)-1) -> 0.13060945 | X10: =(($V130/$V10)^(1/10)-1) -> 0.092503676 | Y10: =W10-X10 -> 0.03810577
A11: 1871.02 | B11: =VALUE(LEFT(A11, 4)) -> 1871 | C11: 2 | D11: =DATE(B11, VALUE(C11), 1) -> 683402 | E11: 4.5 | F11: 0.26 | G11: 0.4 | H11: 12.844641 | I11: =I10+1/12 -> 1871.125 | J11: =J10*11/12+J22*1/12 -> 5.3233333 | K11: =E11*$H$1851/H11 -> 110.16812 | L11: =F11*$H$1851/H11 -> 6.3652692 | M11: =M10*((K11+(L11/12))/K10) -> 110.69856 | N11: =G11*$H$1851/H11 -> 9.7927219 | O11: =N11*(M11/K11) -> 9.839872 | P11: NA | R11: NA | U11: =((J11/J12+J11/1200+((1+J12/1200)^(-119))*(1-J11/J12))) -> 1.0041798 | V11: =V10*U10*H10/H11 -> 0.97442369 | W11: =(($M131/$M11)^(1/10)-1) -> 0.13085848 | X11: =(($V131/$V11)^(1/10)-1) -> 0.094634634 | Y11: =W11-X11 -> 0.036223847
A12: 1871.03 | B12: =VALUE(LEFT(A12, 4)) -> 1871 | C12: 3 | D12: =DATE(B12, VALUE(C12), 1) -> 683430 | E12: 4.61 | F12: 0.26 | G12: 0.4 | H12: 13.034972 | I12: =I11+1/12 -> 1871.2083 | J12: =J10*10/12+J22*2/12 -> 5.3266667 | K12: =E12*$H$1851/H12 -> 111.21317 | L12: =F12*$H$1851/H12 -> 6.2723265 | M12: =M11*((K12+(L12/12))/K11) -> 112.27386 | N12: =G12*$H$1851/H12 -> 9.6497331 | O12: =N12*(M12/K12) -> 9.7417662 | P12: NA | R12: NA | U12: =((J12/J13+J12/1200+((1+J13/1200)^(-119))*(1-J12/J13))) -> 1.0041826 | V12: =V11*U11*H11/H12 -> 0.96420899 | W12: =(($M132/$M12)^(1/10)-1) -> 0.13095087 | X12: =(($V132/$V12)^(1/10)-1) -> 0.096185996 | Y12: =W12-X12 -> 0.034764877
A13: 1871.04 | B13: =VALUE(LEFT(A13, 4)) -> 1871 | C13: 4 | D13: =DATE(B13, VALUE(C13), 1) -> 683461 | E13: 4.74 | F13: 0.26 | G13: 0.4 | H13: 12.559226 | I13: =I12+1/12 -> 1871.2917 | J13: =J10*9/12+J22*3/12 -> 5.33 | K13: =E13*$H$1851/H13 -> 118.68091 | L13: =F13*$H$1851/H13 -> 6.5099232 | M13: =M12*((K13+(L13/12))/K12) -> 120.36048 | N13: =G13*$H$1851/H13 -> 10.015267 | O13: =N13*(M13/K13) -> 10.157002 | P13: NA | R13: NA | U13: =((J13/J14+J13/1200+((1+J14/1200)^(-119))*(1-J13/J14))) -> 1.0041854 | V13: =V12*U12*H12/H13 -> 1.004919 | W13: =(($M133/$M13)^(1/10)-1) -> 0.12205604 | X13: =(($V133/$V13)^(1/10)-1) -> 0.090971906 | Y13: =W13-X13 -> 0.031084131
A14: 1871.05 | B14: =VALUE(LEFT(A14, 4)) -> 1871 | C14: 5 | D14: =DATE(B14, VALUE(C14), 1) -> 683491 | E14: 4.86 | F14: 0.26 | G14: 0.4 | H14: 12.273812 | I14: =I13+1/12 -> 1871.375 | J14: =J10*8/12+J22*4/12 -> 5.3333333 | K14: =E14*$H$1851/H14 -> 124.51516 | L14: =F14*$H$1851/H14 -> 6.6613048 | M14: =M13*((K14+(L14/12))/K13) -> 126.84026 | N14: =G14*$H$1851/H14 -> 10.248161 | O14: =N14*(M14/K14) -> 10.439528 | P14: NA | R14: NA | U14: =((J14/J15+J14/1200+((1+J15/1200)^(-119))*(1-J14/J15))) -> 1.0041882 | V14: =V13*U13*H13/H14 -> 1.0325911 | W14: =(($M134/$M14)^(1/10)-1) -> 0.1226381 | X14: =(($V134/$V14)^(1/10)-1) -> 0.089488437 | Y14: =W14-X14 -> 0.033149662
A15: 1871.06 | B15: =VALUE(LEFT(A15, 4)) -> 1871 | C15: 6 | D15: =DATE(B15, VALUE(C15), 1) -> 683522 | E15: 4.82 | F15: 0.26 | G15: 0.4 | H15: 12.083481 | I15: =I14+1/12 -> 1871.4583 | J15: =J10*7/12+J22*5/12 -> 5.3366667 | K15: =E15*$H$1851/H15 -> 125.43548 | L15: =F15*$H$1851/H15 -> 6.766229 | M15: =M14*((K15+(L15/12))/K14) -> 128.35215 | N15: =G15*$H$1851/H15 -> 10.409583 | O15: =N15*(M15/K15) -> 10.65163 | P15: NA | R15: NA | U15: =((J15/J16+J15/1200+((1+J16/1200)^(-119))*(1-J15/J16))) -> 1.004191 | V15: =V14*U14*H14/H15 -> 1.0532486 | W15: =(($M135/$M15)^(1/10)-1) -> 0.1230928 | X15: =(($V135/$V15)^(1/10)-1) -> 0.087724911 | Y15: =W15-X15 -> 0.035367889
A16: 1871.07 | B16: =VALUE(LEFT(A16, 4)) -> 1871 | C16: 7 | D16: =DATE(B16, VALUE(C16), 1) -> 683552 | E16: 4.73 | F16: 0.26 | G16: 0.4 | H16: 12.083481 | I16: =I15+1/12 -> 1871.5417 | J16: =J10*6/12+J22*6/12 -> 5.34 | K16: =E16*$H$1851/H16 -> 123.09332 | L16: =F16*$H$1851/H16 -> 6.766229 | M16: =M15*((K16+(L16/12))/K15) -> 126.53249 | N16: =G16*$H$1851/H16 -> 10.409583 | O16: =N16*(M16/K16) -> 10.700422 | P16: NA | R16: NA | U16: =((J16/J17+J16/1200+((1+J17/1200)^(-119))*(1-J16/J17))) -> 1.0041938 | V16: =V15*U15*H15/H16 -> 1.0576628 | W16: =(($M136/$M16)^(1/10)-1) -> 0.12002182 | X16: =(($V136/$V16)^(1/10)-1) -> 0.086580856 | Y16: =W16-X16 -> 0.03344096
A17: 1871.08 | B17: =VALUE(LEFT(A17, 4)) -> 1871 | C17: 8 | D17: =DATE(B17, VALUE(C17), 1) -> 683583 | E17: 4.79 | F17: 0.26 | G17: 0.4 | H17: 11.893231 | I17: =I16+1/12 -> 1871.625 | J17: =J10*5/12+J22*7/12 -> 5.3433333 | K17: =E17*$H$1851/H17 -> 126.64879 | L17: =F17*$H$1851/H17 -> 6.8744647 | M17: =M16*((K17+(L17/12))/K16) -> 130.77618 | N17: =G17*$H$1851/H17 -> 10.5761 | O17: =N17*(M17/K17) -> 10.920767 | P17: NA | R17: NA | U17: =((J17/J18+J17/1200+((1+J18/1200)^(-119))*(1-J17/J18))) -> 1.0041967 | V17: =V16*U16*H16/H17 -> 1.0790883 | W17: =(($M137/$M17)^(1/10)-1) -> 0.11193301 | X17: =(($V137/$V17)^(1/10)-1) -> 0.082668611 | Y17: =W17-X17 -> 0.029264399
A18: 1871.09 | B18: =VALUE(LEFT(A18, 4)) -> 1871 | C18: 9 | D18: =DATE(B18, VALUE(C18), 1) -> 683614 | E18: 4.84 | F18: 0.26 | G18: 0.4 | H18: 12.178646 | I18: =I17+1/12 -> 1871.7083 | J18: =J10*4/12+J22*8/12 -> 5.3466667 | K18: =E18*$H$1851/H18 -> 124.97172 | L18: =F18*$H$1851/H18 -> 6.713357 | M18: =M17*((K18+(L18/12))/K17) -> 129.62213 | N18: =G18*$H$1851/H18 -> 10.328242 | O18: =N18*(M18/K18) -> 10.712573 | P18: NA | R18: NA | U18: =((J18/J19+J18/1200+((1+J19/1200)^(-119))*(1-J18/J19))) -> 1.0041995 | V18: =V17*U17*H17/H18 -> 1.0582215 | W18: =(($M138/$M18)^(1/10)-1) -> 0.11002821 | X18: =(($V138/$V18)^(1/10)-1) -> 0.081047905 | Y18: =W18-X18 -> 0.028980301
A19: 1871.1 | B19: =VALUE(LEFT(A19, 4)) -> 1871 | C19: 10 | D19: =DATE(B19, VALUE(C19), 1) -> 683644 | E19: 4.59 | F19: 0.26 | G19: 0.4 | H19: 12.368896 | I19: =I18+1/12 -> 1871.7917 | J19: =J10*3/12+J22*9/12 -> 5.35 | K19: =E19*$H$1851/H19 -> 116.69363 | L19: =F19*$H$1851/H19 -> 6.6100969 | M19: =M18*((K19+(L19/12))/K18) -> 121.60734 | N19: =G19*$H$1851/H19 -> 10.16938 | O19: =N19*(M19/K19) -> 10.59759 | P19: NA | R19: NA | U19: =((J19/J20+J19/1200+((1+J20/1200)^(-119))*(1-J19/J20))) -> 1.0042023 | V19: =V18*U18*H18/H19 -> 1.0463203 | W19: =(($M139/$M19)^(1/10)-1) -> 0.11476526 | X19: =(($V139/$V19)^(1/10)-1) -> 0.081652652 | Y19: =W19-X19 -> 0.033112606
A20: 1871.11 | B20: =VALUE(LEFT(A20, 4)) -> 1871 | C20: 11 | D20: =DATE(B20, VALUE(C20), 1) -> 683675 | E20: 4.64 | F20: 0.26 | G20: 0.4 | H20: 12.368896 | I20: =I19+1/12 -> 1871.875 | J20: =J10*2/12+J22*10/12 -> 5.3533333 | K20: =E20*$H$1851/H20 -> 117.96481 | L20: =F20*$H$1851/H20 -> 6.6100969 | M20: =M19*((K20+(L20/12))/K19) -> 123.50608 | N20: =G20*$H$1851/H20 -> 10.16938 | O20: =N20*(M20/K20) -> 10.647076 | P20: NA | R20: NA | U20: =((J20/J21+J20/1200+((1+J21/1200)^(-119))*(1-J20/J21))) -> 1.0042051 | V20: =V19*U19*H19/H20 -> 1.0507173 | W20: =(($M140/$M20)^(1/10)-1) -> 0.11526992 | X20: =(($V140/$V20)^(1/10)-1) -> 0.08259325 | Y20: =W20-X20 -> 0.032676669
A21: 1871.12 | B21: =VALUE(LEFT(A21, 4)) -> 1871 | C21: 12 | D21: =DATE(B21, VALUE(C21), 1) -> 683705 | E21: 4.74 | F21: 0.26 | G21: 0.4 | H21: 12.654392 | I21: =I20+1/12 -> 1871.9583 | J21: =J10*1/12+J22*11/12 -> 5.3566667 | K21: =E21*$H$1851/H21 -> 117.78839 | L21: =F21*$H$1851/H21 -> 6.4609664 | M21: =M20*((K21+(L21/12))/K20) -> 123.88508 | N21: =G21*$H$1851/H21 -> 9.9399483 | O21: =N21*(M21/K21) -> 10.454437 | P21: NA | R21: NA | U21: =((J21/J22+J21/1200+((1+J22/1200)^(-119))*(1-J21/J22))) -> 1.0042079 | V21: =V20*U20*H20/H21 -> 1.0313307 | W21: =(($M141/$M21)^(1/10)-1) -> 0.11213517 | X21: =(($V141/$V21)^(1/10)-1) -> 0.084999178 | Y21: =W21-X21 -> 0.027135996
A22: 1872.01 | B22: =VALUE(LEFT(A22, 4)) -> 1872 | C22: 1 | D22: =DATE(B22, VALUE(C22), 1) -> 683736 | E22: 4.86 | F22: 0.2633 | G22: 0.4025 | H22: 12.654392 | I22: =I21+1/12 -> 1872.0417 | J22: 5.36 | K22: =E22*$H$1851/H22 -> 120.77037 | L22: =F22*$H$1851/H22 -> 6.542971 | M22: =M21*((K22+(L22/12))/K21) -> 127.59488 | N22: =G22*$H$1851/H22 -> 10.002073 | O22: =N22*(M22/K22) -> 10.567271 | P22: NA | R22: NA | U22: =((J22/J23+J22/1200+((1+J23/1200)^(-119))*(1-J22/J23))) -> 1.00306 | V22: =V21*U21*H21/H22 -> 1.0356705 | W22: =(($M142/$M22)^(1/10)-1) -> 0.10768446 | X22: =(($V142/$V22)^(1/10)-1) -> 0.084930989 | Y22: =W22-X22 -> 0.022753475
A23: 1872.02 | B23: =VALUE(LEFT(A23, 4)) -> 1872 | C23: 2 | D23: =DATE(B23, VALUE(C23), 1) -> 683767 | E23: 4.88 | F23: 0.2667 | G23: 0.405 | H23: 12.654392 | I23: =I22+1/12 -> 1872.125 | J23: =J22*11/12+J34*1/12 -> 5.3783333 | K23: =E23*$H$1851/H23 -> 121.26737 | L23: =F23*$H$1851/H23 -> 6.6274605 | M23: =M22*((K23+(L23/12))/K22) -> 128.70346 | N23: =G23*$H$1851/H23 -> 10.064198 | O23: =N23*(M23/K23) -> 10.681332 | P23: NA | R23: NA | U23: =((J23/J24+J23/1200+((1+J24/1200)^(-119))*(1-J23/J24))) -> 1.0030764 | V23: =V22*U22*H22/H23 -> 1.0388396 | W23: =(($M143/$M23)^(1/10)-1) -> 0.10375208 | X23: =(($V143/$V23)^(1/10)-1) -> 0.083909829 | Y23: =W23-X23 -> 0.019842247
A24: 1872.03 | B24: =VALUE(LEFT(A24, 4)) -> 1872 | C24: 3 | D24: =DATE(B24, VALUE(C24), 1) -> 683796 | E24: 5.04 | F24: 0.27 | G24: 0.4075 | H24: 12.844641 | I24: =I23+1/12 -> 1872.2083 | J24: =J22*10/12+J34*2/12 -> 5.3966667 | K24: =E24*$H$1851/H24 -> 123.3883 | L24: =F24*$H$1851/H24 -> 6.6100873 | M24: =M23*((K24+(L24/12))/K23) -> 131.53906 | N24: =G24*$H$1851/H24 -> 9.9763354 | O24: =N24*(M24/K24) -> 10.63535 | P24: NA | R24: NA | U24: =((J24/J25+J24/1200+((1+J25/1200)^(-119))*(1-J24/J25))) -> 1.0030929 | V24: =V23*U23*H23/H24 -> 1.0266014 | W24: =(($M144/$M24)^(1/10)-1) -> 0.10166592 | X24: =(($V144/$V24)^(1/10)-1) -> 0.085514588 | Y24: =W24-X24 -> 0.016151334
A25: 1872.04 | B25: =VALUE(LEFT(A25, 4)) -> 1872 | C25: 4 | D25: =DATE(B25, VALUE(C25), 1) -> 683827 | E25: 5.18 | F25: 0.2733 | G25: 0.41 | H25: 13.130137 | I25: =I24+1/12 -> 1872.2917 | J25: =J22*9/12+J34*3/12 -> 5.415 | K25: =E25*$H$1851/H25 -> 124.05832 | L25: =F25*$H$1851/H25 -> 6.5453938 | M25: =M24*((K25+(L25/12))/K24) -> 132.83482 | N25: =G25*$H$1851/H25 -> 9.8192881 | O25: =N25*(M25/K25) -> 10.513953 | P25: NA | R25: NA | U25: =((J25/J26+J25/1200+((1+J26/1200)^(-119))*(1-J25/J26))) -> 1.0031093 | V25: =V24*U24*H24/H25 -> 1.0073855 | W25: =(($M145/$M25)^(1/10)-1) -> 0.10007867 | X25: =(($V145/$V25)^(1/10)-1) -> 0.086885498 | Y25: =W25-X25 -> 0.01319317
A26: 1872.05 | B26: =VALUE(LEFT(A26, 4)) -> 1872 | C26: 5 | D26: =DATE(B26, VALUE(C26), 1) -> 683857 | E26: 5.18 | F26: 0.2767 | G26: 0.4125 | H26: 13.130137 | I26: =I25+1/12 -> 1872.375 | J26: =J22*8/12+J34*4/12 -> 5.4333333 | K26: =E26*$H$1851/H26 -> 124.05832 | L26: =F26*$H$1851/H26 -> 6.626822 | M26: =M25*((K26+(L26/12))/K25) -> 133.42613 | N26: =G26*$H$1851/H26 -> 9.8791618 | O26: =N26*(M26/K26) -> 10.62515 | P26: NA | R26: NA | U26: =((J26/J27+J26/1200+((1+J27/1200)^(-119))*(1-J26/J27))) -> 1.0031258 | V26: =V25*U25*H25/H26 -> 1.0105178 | W26: =(($M146/$M26)^(1/10)-1) -> 0.097760664 | X26: =(($V146/$V26)^(1/10)-1) -> 0.085876681 | Y26: =W26-X26 -> 0.011883983
A27: 1872.06 | B27: =VALUE(LEFT(A27, 4)) -> 1872 | C27: 6 | D27: =DATE(B27, VALUE(C27), 1) -> 683888 | E27: 5.13 | F27: 0.28 | G27: 0.415 | H27: 13.034972 | I27: =I26+1/12 -> 1872.4583 | J27: =J22*7/12+J34*5/12 -> 5.4516667 | K27: =E27*$H$1851/H27 -> 123.75783 | L27: =F27*$H$1851/H27 -> 6.7548132 | M27: =M26*((K27+(L27/12))/K26) -> 133.70835 | N27: =G27*$H$1851/H27 -> 10.011598 | O27: =N27*(M27/K27) -> 10.816562 | P27: NA | R27: NA | U27: =((J27/J28+J27/1200+((1+J28/1200)^(-119))*(1-J27/J28))) -> 1.0031422 | V27: =V26*U26*H26/H27 -> 1.0210771 | W27: =(($M147/$M27)^(1/10)-1) -> 0.096471706 | X27: =(($V147/$V27)^(1/10)-1) -> 0.084086342 | Y27: =W27-X27 -> 0.012385364
A28: 1872.07 | B28: =VALUE(LEFT(A28, 4)) -> 1872 | C28: 7 | D28: =DATE(B28, VALUE(C28), 1) -> 683918 | E28: 5.1 | F28: 0.2833 | G28: 0.4175 | H28: 12.844641 | I28: =I27+1/12 -> 1872.5417 | J28: =J22*6/12+J34*6/12 -> 5.47 | K28: =E28*$H$1851/H28 -> 124.8572 | L28: =F28*$H$1851/H28 -> 6.9356953 | M28: =M27*((K28+(L28/12))/K27) -> 135.52056 | N28: =G28*$H$1851/H28 -> 10.221153 | O28: =N28*(M28/K28) -> 11.094085 | P28: NA | R28: NA | U28: =((J28/J29+J28/1200+((1+J29/1200)^(-119))*(1-J28/J29))) -> 1.0031587 | V28: =V27*U27*H27/H28 -> 1.0394633 | W28: =(($M148/$M28)^(1/10)-1) -> 0.1025004 | X28: =(($V148/$V28)^(1/10)-1) -> 0.083452521 | Y28: =W28-X28 -> 0.019047881
A29: 1872.08 | B29: =VALUE(LEFT(A29, 4)) -> 1872 | C29: 8 | D29: =DATE(B29, VALUE(C29), 1) -> 683949 | E29: 5.04 | F29: 0.2867 | G29: 0.42 | H29: 12.939807 | I29: =I28+1/12 -> 1872.625 | J29: =J22*5/12+J34*7/12 -> 5.4883333 | K29: =E29*$H$1851/H29 -> 122.48084 | L29: =F29*$H$1851/H29 -> 6.9673129 | M29: =M28*((K29+(L29/12))/K28) -> 133.57144 | N29: =G29*$H$1851/H29 -> 10.206737 | O29: =N29*(M29/K29) -> 11.130954 | P29: NA | R29: NA | U29: =((J29/J30+J29/1200+((1+J30/1200)^(-119))*(1-J29/J30))) -> 1.0031751 | V29: =V28*U28*H28/H29 -> 1.0350778 | W29: =(($M149/$M29)^(1/10)-1) -> 0.10684172 | X29: =(($V149/$V29)^(1/10)-1) -> 0.083249218 | Y29: =W29-X29 -> 0.0235925
A30: 1872.09 | B30: =VALUE(LEFT(A30, 4)) -> 1872 | C30: 9 | D30: =DATE(B30, VALUE(C30), 1) -> 683980 | E30: 4.95 | F30: 0.29 | G30: 0.4225 | H30: 13.034972 | I30: =I29+1/12 -> 1872.7083 | J30: =J22*4/12+J34*8/12 -> 5.5066667 | K30: =E30*$H$1851/H30 -> 119.41545 | L30: =F30*$H$1851/H30 -> 6.9960565 | M30: =M29*((K30+(L30/12))/K29) -> 130.86428 | N30: =G30*$H$1851/H30 -> 10.192531 | O30: =N30*(M30/K30) -> 11.169729 | P30: NA | R30: NA | U30: =((J30/J31+J30/1200+((1+J31/1200)^(-119))*(1-J30/J31))) -> 1.0031915 | V30: =V29*U29*H29/H30 -> 1.0307834 | W30: =(($M150/$M30)^(1/10)-1) -> 0.11370306 | X30: =(($V150/$V30)^(1/10)-1) -> 0.086993117 | Y30: =W30-X30 -> 0.026709944
A31: 1872.1 | B31: =VALUE(LEFT(A31, 4)) -> 1872 | C31: 10 | D31: =DATE(B31, VALUE(C31), 1) -> 684010 | E31: 4.97 | F31: 0.2933 | G31: 0.425 | H31: 12.749476 | I31: =I30+1/12 -> 1872.7917 | J31: =J22*3/12+J34*9/12 -> 5.525 | K31: =E31*$H$1851/H31 -> 122.58278 | L31: =F31*$H$1851/H31 -> 7.2341105 | M31: =M30*((K31+(L31/12))/K30) -> 134.99591 | N31: =G31*$H$1851/H31 -> 10.482431 | O31: =N31*(M31/K31) -> 11.543916 | P31: NA | R31: NA | U31: =((J31/J32+J31/1200+((1+J32/1200)^(-119))*(1-J31/J32))) -> 1.003208 | V31: =V30*U30*H30/H31 -> 1.057229 | W31: =(($M151/$M31)^(1/10)-1) -> 0.10870072 | X31: =(($V151/$V31)^(1/10)-1) -> 0.085572333 | Y31: =W31-X31 -> 0.023128387
A32: 1872.11 | B32: =VALUE(LEFT(A32, 4)) -> 1872 | C32: 11 | D32: =DATE(B32, VALUE(C32), 1) -> 684041 | E32: 4.95 | F32: 0.2967 | G32: 0.4275 | H32: 13.130137 | I32: =I31+1/12 -> 1872.875 | J32: =J22*2/12+J34*10/12 -> 5.5433333 | K32: =E32*$H$1851/H32 -> 118.54994 | L32: =F32*$H$1851/H32 -> 7.1058117 | M32: =M31*((K32+(L32/12))/K31) -> 131.20681 | N32: =G32*$H$1851/H32 -> 10.238404 | O32: =N32*(M32/K32) -> 11.331497 | P32: NA | R32: NA | U32: =((J32/J33+J32/1200+((1+J33/1200)^(-119))*(1-J32/J33))) -> 1.0032244 | V32: =V31*U31*H31/H32 -> 1.0298717 | W32: =(($M152/$M32)^(1/10)-1) -> 0.10855246 | X32: =(($V152/$V32)^(1/10)-1) -> 0.089766168 | Y32: =W32-X32 -> 0.01878629
A33: 1872.12 | B33: =VALUE(LEFT(A33, 4)) -> 1872 | C33: 12 | D33: =DATE(B33, VALUE(C33), 1) -> 684071 | E33: 5.07 | F33: 0.3 | G33: 0.43 | H33: 12.939807 | I33: =I32+1/12 -> 1872.9583 | J33: =J22*1/12+J34*11/12 -> 5.5616667 | K33: =E33*$H$1851/H33 -> 123.20989 | L33: =F33*$H$1851/H33 -> 7.2905263 | M33: =M32*((K33+(L33/12))/K32) -> 137.03668 | N33: =G33*$H$1851/H33 -> 10.449754 | O33: =N33*(M33/K33) -> 11.622441 | P33: NA | R33: NA | U33: =((J33/J34+J33/1200+((1+J34/1200)^(-119))*(1-J33/J34))) -> 1.0032409 | V33: =V32*U32*H32/H33 -> 1.0483896 | W33: =(($M153/$M33)^(1/10)-1) -> 0.10586247 | X33: =(($V153/$V33)^(1/10)-1) -> 0.08917802 | Y33: =W33-X33 -> 0.016684455
A34: 1873.01 | B34: =VALUE(LEFT(A34, 4)) -> 1873 | C34: 1 | D34: =DATE(B34, VALUE(C34), 1) -> 684102 | E34: 5.11 | F34: 0.3025 | G34: 0.4325 | H34: 12.939807 | I34: =I33+1/12 -> 1873.0417 | J34: 5.58 | K34: =E34*$H$1851/H34 -> 124.18196 | L34: =F34*$H$1851/H34 -> 7.3512807 | M34: =M33*((K34+(L34/12))/K33) -> 138.7992 | N34: =G34*$H$1851/H34 -> 10.510509 | O34: =N34*(M34/K34) -> 11.747681 | P34: NA | R34: NA | U34: =((J34/J35+J34/1200+((1+J35/1200)^(-119))*(1-J34/J35))) -> 1.0053472 | V34: =V33*U33*H33/H34 -> 1.0517872 | W34: =(($M154/$M34)^(1/10)-1) -> 0.10438834 | X34: =(($V154/$V34)^(1/10)-1) -> 0.089146981 | Y34: =W34-X34 -> 0.015241355
A35: 1873.02 | B35: =VALUE(LEFT(A35, 4)) -> 1873 | C35: 2 | D35: =DATE(B35, VALUE(C35), 1) -> 684133 | E35: 5.15 | F35: 0.305 | G35: 0.435 | H35: 13.225221 | I35: =I34+1/12 -> 1873.125 | J35: =J34*11/12+J46*1/12 -> 5.5708333 | K35: =E35*$H$1851/H35 -> 122.45307 | L35: =F35*$H$1851/H35 -> 7.2520751 | M35: =M34*((K35+(L35/12))/K34) -> 137.54227 | N35: =G35*$H$1851/H35 -> 10.343124 | O35: =N35*(M35/K35) -> 11.617648 | P35: NA | R35: NA | U35: =((J35/J36+J35/1200+((1+J36/1200)^(-119))*(1-J35/J36))) -> 1.0053399 | V35: =V34*U34*H34/H35 -> 1.0345913 | W35: =(($M155/$M35)^(1/10)-1) -> 0.10236955 | X35: =(($V155/$V35)^(1/10)-1) -> 0.090247719 | Y35: =W35-X35 -> 0.012121836
A36: 1873.03 | B36: =VALUE(LEFT(A36, 4)) -> 1873 | C36: 3 | D36: =DATE(B36, VALUE(C36), 1) -> 684161 | E36: 5.11 | F36: 0.3075 | G36: 0.4375 | H36: 13.225221 | I36: =I35+1/12 -> 1873.2083 | J36: =J34*10/12+J46*2/12 -> 5.5616667 | K36: =E36*$H$1851/H36 -> 121.50198 | L36: =F36*$H$1851/H36 -> 7.3115184 | M36: =M35*((K36+(L36/12))/K35) -> 137.15836 | N36: =G36*$H$1851/H36 -> 10.402567 | O36: =N36*(M36/K36) -> 11.74301 | P36: NA | R36: NA | U36: =((J36/J37+J36/1200+((1+J37/1200)^(-119))*(1-J36/J37))) -> 1.0053325 | V36: =V35*U35*H35/H36 -> 1.0401159 | W36: =(($M156/$M36)^(1/10)-1) -> 0.1055909 | X36: =(($V156/$V36)^(1/10)-1) -> 0.091036887 | Y36: =W36-X36 -> 0.014554018
A37: 1873.04 | B37: =VALUE(LEFT(A37, 4)) -> 1873 | C37: 4 | D37: =DATE(B37, VALUE(C37), 1) -> 684192 | E37: 5.04 | F37: 0.31 | G37: 0.44 | H37: 13.225221 | I37: =I36+1/12 -> 1873.2917 | J37: =J34*9/12+J46*3/12 -> 5.5525 | K37: =E37*$H$1851/H37 -> 119.83757 | L37: =F37*$H$1851/H37 -> 7.3709616 | M37: =M36*((K37+(L37/12))/K36) -> 135.97287 | N37: =G37*$H$1851/H37 -> 10.46201 | O37: =N37*(M37/K37) -> 11.870648 | P37: NA | R37: NA | U37: =((J37/J38+J37/1200+((1+J38/1200)^(-119))*(1-J37/J38))) -> 1.0053252 | V37: =V36*U36*H36/H37 -> 1.0456623 | W37: =(($M157/$M37)^(1/10)-1) -> 0.11040916 | X37: =(($V157/$V37)^(1/10)-1) -> 0.091838133 | Y37: =W37-X37 -> 0.01857103
A38: 1873.05 | B38: =VALUE(LEFT(A38, 4)) -> 1873 | C38: 5 | D38: =DATE(B38, VALUE(C38), 1) -> 684222 | E38: 5.05 | F38: 0.3125 | G38: 0.4425 | H38: 12.939807 | I38: =I37+1/12 -> 1873.375 | J38: =J34*8/12+J46*4/12 -> 5.5433333 | K38: =E38*$H$1851/H38 -> 122.72386 | L38: =F38*$H$1851/H38 -> 7.5942982 | M38: =M37*((K38+(L38/12))/K37) -> 139.96585 | N38: =G38*$H$1851/H38 -> 10.753526 | O38: =N38*(M38/K38) -> 12.264334 | P38: NA | R38: NA | U38: =((J38/J39+J38/1200+((1+J39/1200)^(-119))*(1-J38/J39))) -> 1.0053178 | V38: =V37*U37*H37/H38 -> 1.0744178 | W38: =(($M158/$M38)^(1/10)-1) -> 0.10688474 | X38: =(($V158/$V38)^(1/10)-1) -> 0.090269519 | Y38: =W38-X38 -> 0.016615217
A39: 1873.06 | B39: =VALUE(LEFT(A39, 4)) -> 1873 | C39: 6 | D39: =DATE(B39, VALUE(C39), 1) -> 684253 | E39: 4.98 | F39: 0.315 | G39: 0.445 | H39: 12.559226 | I39: =I38+1/12 -> 1873.4583 | J39: =J34*7/12+J46*5/12 -> 5.5341667 | K39: =E39*$H$1851/H39 -> 124.69007 | L39: =F39*$H$1851/H39 -> 7.8870224 | M39: =M38*((K39+(L39/12))/K38) -> 142.95789 | N39: =G39*$H$1851/H39 -> 11.141984 | O39: =N39*(M39/K39) -> 12.77435 | P39: NA | R39: NA | U39: =((J39/J40+J39/1200+((1+J40/1200)^(-119))*(1-J39/J40))) -> 1.0053105 | V39: =V38*U38*H38/H39 -> 1.1128624 | W39: =(($M159/$M39)^(1/10)-1) -> 0.10928659 | X39: =(($V159/$V39)^(1/10)-1) -> 0.089995543 | Y39: =W39-X39 -> 0.019291046
A40: 1873.07 | B40: =VALUE(LEFT(A40, 4)) -> 1873 | C40: 7 | D40: =DATE(B40, VALUE(C40), 1) -> 684283 | E40: 4.97 | F40: 0.3175 | G40: 0.4475 | H40: 12.559226 | I40: =I39+1/12 -> 1873.5417 | J40: =J34*6/12+J46*6/12 -> 5.525 | K40: =E40*$H$1851/H40 -> 124.43969 | L40: =F40*$H$1851/H40 -> 7.9496178 | M40: =M39*((K40+(L40/12))/K39) -> 143.43035 | N40: =G40*$H$1851/H40 -> 11.204579 | O40: =N40*(M40/K40) -> 12.914503 | P40: NA | R40: NA | U40: =((J40/J41+J40/1200+((1+J41/1200)^(-119))*(1-J40/J41))) -> 1.0053031 | V40: =V39*U39*H39/H40 -> 1.1187722 | W40: =(($M160/$M40)^(1/10)-1) -> 0.10995788 | X40: =(($V160/$V40)^(1/10)-1) -> 0.091958924 | Y40: =W40-X40 -> 0.017998957
A41: 1873.08 | B41: =VALUE(LEFT(A41, 4)) -> 1873 | C41: 8 | D41: =DATE(B41, VALUE(C41), 1) -> 684314 | E41: 4.97 | F41: 0.32 | G41: 0.45 | H41: 12.559226 | I41: =I40+1/12 -> 1873.625 | J41: =J34*5/12+J46*7/12 -> 5.5158333 | K41: =E41*$H$1851/H41 -> 124.43969 | L41: =F41*$H$1851/H41 -> 8.0122132 | M41: =M40*((K41+(L41/12))/K40) -> 144.19993 | N41: =G41*$H$1851/H41 -> 11.267175 | O41: =N41*(M41/K41) -> 13.056332 | P41: NA | R41: NA | U41: =((J41/J42+J41/1200+((1+J42/1200)^(-119))*(1-J41/J42))) -> 1.0052958 | V41: =V40*U40*H40/H41 -> 1.1247052 | W41: =(($M161/$M41)^(1/10)-1) -> 0.10477284 | X41: =(($V161/$V41)^(1/10)-1) -> 0.091718314 | Y41: =W41-X41 -> 0.013054527
A42: 1873.09 | B42: =VALUE(LEFT(A42, 4)) -> 1873 | C42: 9 | D42: =DATE(B42, VALUE(C42), 1) -> 684345 | E42: 4.59 | F42: 0.3225 | G42: 0.4525 | H42: 12.559226 | I42: =I41+1/12 -> 1873.7083 | J42: =J34*4/12+J46*8/12 -> 5.5066667 | K42: =E42*$H$1851/H42 -> 114.92518 | L42: =F42*$H$1851/H42 -> 8.0748086 | M42: =M41*((K42+(L42/12))/K41) -> 133.95434 | N42: =G42*$H$1851/H42 -> 11.32977 | O42: =N42*(M42/K42) -> 13.205738 | P42: NA | R42: NA | U42: =((J42/J43+J42/1200+((1+J43/1200)^(-119))*(1-J42/J43))) -> 1.0052884 | V42: =V41*U41*H41/H42 -> 1.1306614 | W42: =(($M162/$M42)^(1/10)-1) -> 0.11585286 | X42: =(($V162/$V42)^(1/10)-1) -> 0.092598763 | Y42: =W42-X42 -> 0.023254096
A43: 1873.1 | B43: =VALUE(LEFT(A43, 4)) -> 1873 | C43: 10 | D43: =DATE(B43, VALUE(C43), 1) -> 684375 | E43: 4.19 | F43: 0.325 | G43: 0.455 | H43: 12.273812 | I43: =I42+1/12 -> 1873.7917 | J43: =J34*3/12+J46*9/12 -> 5.4975 | K43: =E43*$H$1851/H43 -> 107.34949 | L43: =F43*$H$1851/H43 -> 8.326631 | M43: =M42*((K43+(L43/12))/K42) -> 125.93305 | N43: =G43*$H$1851/H43 -> 11.657283 | O43: =N43*(M43/K43) -> 13.675307 | P43: NA | R43: NA | U43: =((J43/J44+J43/1200+((1+J44/1200)^(-119))*(1-J43/J44))) -> 1.0052811 | V43: =V42*U42*H42/H43 -> 1.1630722 | W43: =(($M163/$M43)^(1/10)-1) -> 0.12024919 | X43: =(($V163/$V43)^(1/10)-1) -> 0.089851257 | Y43: =W43-X43 -> 0.030397933
A44: 1873.11 | B44: =VALUE(LEFT(A44, 4)) -> 1873 | C44: 11 | D44: =DATE(B44, VALUE(C44), 1) -> 684406 | E44: 4.04 | F44: 0.3275 | G44: 0.4575 | H44: 11.893231 | I44: =I43+1/12 -> 1873.875 | J44: =J34*2/12+J46*10/12 -> 5.4883333 | K44: =E44*$H$1851/H44 -> 106.81861 | L44: =F44*$H$1851/H44 -> 8.6591816 | M44: =M43*((K44+(L44/12))/K43) -> 126.15678 | N44: =G44*$H$1851/H44 -> 12.096414 | O44: =N44*(M44/K44) -> 14.286318 | P44: NA | R44: NA | U44: =((J44/J45+J44/1200+((1+J45/1200)^(-119))*(1-J44/J45))) -> 1.0052737 | V44: =V43*U43*H43/H44 -> 1.206629 | W44: =(($M164/$M44)^(1/10)-1) -> 0.12342998 | X44: =(($V164/$V44)^(1/10)-1) -> 0.087312017 | Y44: =W44-X44 -> 0.036117963
A45: 1873.12 | B45: =VALUE(LEFT(A45, 4)) -> 1873 | C45: 12 | D45: =DATE(B45, VALUE(C45), 1) -> 684436 | E45: 4.42 | F45: 0.33 | G45: 0.46 | H45: 12.178646 | I45: =I44+1/12 -> 1873.9583 | J45: =J34*1/12+J46*11/12 -> 5.4791667 | K45: =E45*$H$1851/H45 -> 114.12707 | L45: =F45*$H$1851/H45 -> 8.5207992 | M45: =M44*((K45+(L45/12))/K44) -> 135.62696 | N45: =G45*$H$1851/H45 -> 11.877478 | O45: =N45*(M45/K45) -> 14.115023 | P45: NA | R45: NA | U45: =((J45/J46+J45/1200+((1+J46/1200)^(-119))*(1-J45/J46))) -> 1.0052664 | V45: =V44*U44*H44/H45 -> 1.1845652 | W45: =(($M165/$M45)^(1/10)-1) -> 0.11227108 | X45: =(($V165/$V45)^(1/10)-1) -> 0.088528455 | Y45: =W45-X45 -> 0.023742626
A46: 1874.01 | B46: =VALUE(LEFT(A46, 4)) -> 1874 | C46: 1 | D46: =DATE(B46, VALUE(C46), 1) -> 684467 | E46: 4.66 | F46: 0.33 | G46: 0.46 | H46: 12.368896 | I46: =I45+1/12 -> 1874.0417 | J46: 5.47 | K46: =E46*$H$1851/H46 -> 118.47327 | L46: =F46*$H$1851/H46 -> 8.3897383 | M46: =M45*((K46+(L46/12))/K45) -> 141.62279 | N46: =G46*$H$1851/H46 -> 11.694787 | O46: =N46*(M46/K46) -> 13.979932 | P46: NA | R46: NA | U46: =((J46/J47+J46/1200+((1+J47/1200)^(-119))*(1-J46/J47))) -> 1.0071091 | V46: =V45*U45*H45/H46 -> 1.1724875 | W46: =(($M166/$M46)^(1/10)-1) -> 0.1046878 | X46: =(($V166/$V46)^(1/10)-1) -> 0.089980453 | Y46: =W46-X46 -> 0.014707345
A47: 1874.02 | B47: =VALUE(LEFT(A47, 4)) -> 1874 | C47: 2 | D47: =DATE(B47, VALUE(C47), 1) -> 684498 | E47: 4.8 | F47: 0.33 | G47: 0.46 | H47: 12.368896 | I47: =I46+1/12 -> 1874.125 | J47: =J46*11/12+J58*1/12 -> 5.4366667 | K47: =E47*$H$1851/H47 -> 122.03256 | L47: =F47*$H$1851/H47 -> 8.3897383 | M47: =M46*((K47+(L47/12))/K46) -> 146.7133 | N47: =G47*$H$1851/H47 -> 11.694787 | O47: =N47*(M47/K47) -> 14.060025 | P47: NA | R47: NA | U47: =((J47/J48+J47/1200+((1+J48/1200)^(-119))*(1-J47/J48))) -> 1.0070852 | V47: =V46*U46*H46/H47 -> 1.1808228 | W47: =(($M167/$M47)^(1/10)-1) -> 0.10429674 | X47: =(($V167/$V47)^(1/10)-1) -> 0.08961205 | Y47: =W47-X47 -> 0.01468469
A48: 1874.03 | B48: =VALUE(LEFT(A48, 4)) -> 1874 | C48: 3 | D48: =DATE(B48, VALUE(C48), 1) -> 684526 | E48: 4.73 | F48: 0.33 | G48: 0.46 | H48: 12.368896 | I48: =I47+1/12 -> 1874.2083 | J48: =J46*10/12+J58*2/12 -> 5.4033333 | K48: =E48*$H$1851/H48 -> 120.25292 | L48: =F48*$H$1851/H48 -> 8.3897383 | M48: =M47*((K48+(L48/12))/K47) -> 145.41428 | N48: =G48*$H$1851/H48 -> 11.694787 | O48: =N48*(M48/K48) -> 14.141769 | P48: NA | R48: NA | U48: =((J48/J49+J48/1200+((1+J49/1200)^(-119))*(1-J48/J49))) -> 1.0070613 | V48: =V47*U47*H47/H48 -> 1.1891892 | W48: =(($M168/$M48)^(1/10)-1) -> 0.10542637 | X48: =(($V168/$V48)^(1/10)-1) -> 0.089245635 | Y48: =W48-X48 -> 0.016180734
A49: 1874.04 | B49: =VALUE(LEFT(A49, 4)) -> 1874 | C49: 4 | D49: =DATE(B49, VALUE(C49), 1) -> 684557 | E49: 4.6 | F49: 0.33 | G49: 0.46 | H49: 12.178646 | I49: =I48+1/12 -> 1874.2917 | J49: =J46*9/12+J58*3/12 -> 5.37 | K49: =E49*$H$1851/H49 -> 118.77478 | L49: =F49*$H$1851/H49 -> 8.5207992 | M49: =M48*((K49+(L49/12))/K48) -> 144.4855 | N49: =G49*$H$1851/H49 -> 11.877478 | O49: =N49*(M49/K49) -> 14.44855 | P49: NA | R49: NA | U49: =((J49/J50+J49/1200+((1+J50/1200)^(-119))*(1-J49/J50))) -> 1.0070374 | V49: =V48*U48*H48/H49 -> 1.2162947 | W49: =(($M169/$M49)^(1/10)-1) -> 0.10390272 | X49: =(($V169/$V49)^(1/10)-1) -> 0.089461596 | Y49: =W49-X49 -> 0.014441128
A50: 1874.05 | B50: =VALUE(LEFT(A50, 4)) -> 1874 | C50: 5 | D50: =DATE(B50, VALUE(C50), 1) -> 684587 | E50: 4.48 | F50: 0.33 | G50: 0.46 | H50: 12.083481 | I50: =I49+1/12 -> 1874.375 | J50: =J46*8/12+J58*4/12 -> 5.3366667 | K50: =E50*$H$1851/H50 -> 116.58733 | L50: =F50*$H$1851/H50 -> 8.5879061 | M50: =M49*((K50+(L50/12))/K49) -> 142.69512 | N50: =G50*$H$1851/H50 -> 11.971021 | O50: =N50*(M50/K50) -> 14.651731 | P50: NA | R50: NA | U50: =((J50/J51+J50/1200+((1+J51/1200)^(-119))*(1-J50/J51))) -> 1.0070135 | V50: =V49*U49*H49/H50 -> 1.2345008 | W50: =(($M170/$M50)^(1/10)-1) -> 0.09894633 | X50: =(($V170/$V50)^(1/10)-1) -> 0.090563363 | Y50: =W50-X50 -> 0.0083829671
A51: 1874.06 | B51: =VALUE(LEFT(A51, 4)) -> 1874 | C51: 6 | D51: =DATE(B51, VALUE(C51), 1) -> 684618 | E51: 4.46 | F51: 0.33 | G51: 0.46 | H51: 11.798066 | I51: =I50+1/12 -> 1874.4583 | J51: =J46*7/12+J58*5/12 -> 5.3033333 | K51: =E51*$H$1851/H51 -> 118.8747 | L51: =F51*$H$1851/H51 -> 8.7956618 | M51: =M50*((K51+(L51/12))/K50) -> 146.39182 | N51: =G51*$H$1851/H51 -> 12.26062 | O51: =N51*(M51/K51) -> 15.098708 | P51: NA | R51: NA | U51: =((J51/J52+J51/1200+((1+J52/1200)^(-119))*(1-J51/J52))) -> 1.0069896 | V51: =V50*U50*H50/H51 -> 1.2732331 | W51: =(($M171/$M51)^(1/10)-1) -> 0.092226727 | X51: =(($V171/$V51)^(1/10)-1) -> 0.087599342 | Y51: =W51-X51 -> 0.0046273848
A52: 1874.07 | B52: =VALUE(LEFT(A52, 4)) -> 1874 | C52: 7 | D52: =DATE(B52, VALUE(C52), 1) -> 684648 | E52: 4.46 | F52: 0.33 | G52: 0.46 | H52: 11.893231 | I52: =I51+1/12 -> 1874.5417 | J52: =J46*6/12+J58*6/12 -> 5.27 | K52: =E52*$H$1851/H52 -> 117.92351 | L52: =F52*$H$1851/H52 -> 8.7252822 | M52: =M51*((K52+(L52/12))/K51) -> 146.11586 | N52: =G52*$H$1851/H52 -> 12.162515 | O52: =N52*(M52/K52) -> 15.070246 | P52: NA | R52: NA | U52: =((J52/J53+J52/1200+((1+J53/1200)^(-119))*(1-J52/J53))) -> 1.0069658 | V52: =V51*U51*H51/H52 -> 1.2718734 | W52: =(($M172/$M52)^(1/10)-1) -> 0.0942624 | X52: =(($V172/$V52)^(1/10)-1) -> 0.089291082 | Y52: =W52-X52 -> 0.0049713181
A53: 1874.08 | B53: =VALUE(LEFT(A53, 4)) -> 1874 | C53: 8 | D53: =DATE(B53, VALUE(C53), 1) -> 684679 | E53: 4.47 | F53: 0.33 | G53: 0.46 | H53: 11.798066 | I53: =I52+1/12 -> 1874.625 | J53: =J46*5/12+J58*7/12 -> 5.2366667 | K53: =E53*$H$1851/H53 -> 119.14124 | L53: =F53*$H$1851/H53 -> 8.7956618 | M53: =M52*((K53+(L53/12))/K52) -> 148.53292 | N53: =G53*$H$1851/H53 -> 12.26062 | O53: =N53*(M53/K53) -> 15.285267 | P53: NA | R53: NA | U53: =((J53/J54+J53/1200+((1+J54/1200)^(-119))*(1-J53/J54))) -> 1.0069419 | V53: =V52*U52*H52/H53 -> 1.2910636 | W53: =(($M173/$M53)^(1/10)-1) -> 0.099751158 | X53: =(($V173/$V53)^(1/10)-1) -> 0.088059593 | Y53: =W53-X53 -> 0.011691564
A54: 1874.09 | B54: =VALUE(LEFT(A54, 4)) -> 1874 | C54: 9 | D54: =DATE(B54, VALUE(C54), 1) -> 684710 | E54: 4.54 | F54: 0.33 | G54: 0.46 | H54: 11.798066 | I54: =I53+1/12 -> 1874.7083 | J54: =J46*4/12+J58*8/12 -> 5.2033333 | K54: =E54*$H$1851/H54 -> 121.00698 | L54: =F54*$H$1851/H54 -> 8.7956618 | M54: =M53*((K54+(L54/12))/K53) -> 151.77273 | N54: =G54*$H$1851/H54 -> 12.26062 | O54: =N54*(M54/K54) -> 15.377854 | P54: NA | R54: NA | U54: =((J54/J55+J54/1200+((1+J55/1200)^(-119))*(1-J54/J55))) -> 1.006918 | V54: =V53*U53*H53/H54 -> 1.300026 | W54: =(($M174/$M54)^(1/10)-1) -> 0.095678559 | X54: =(($V174/$V54)^(1/10)-1) -> 0.088894496 | Y54: =W54-X54 -> 0.006784063
A55: 1874.1 | B55: =VALUE(LEFT(A55, 4)) -> 1874 | C55: 10 | D55: =DATE(B55, VALUE(C55), 1) -> 684740 | E55: 4.53 | F55: 0.33 | G55: 0.46 | H55: 11.607736 | I55: =I54+1/12 -> 1874.7917 | J55: =J46*3/12+J58*9/12 -> 5.17 | K55: =E55*$H$1851/H55 -> 122.72021 | L55: =F55*$H$1851/H55 -> 8.9398832 | M55: =M54*((K55+(L55/12))/K54) -> 154.85595 | N55: =G55*$H$1851/H55 -> 12.461655 | O55: =N55*(M55/K55) -> 15.724887 | P55: NA | R55: NA | U55: =((J55/J56+J55/1200+((1+J56/1200)^(-119))*(1-J55/J56))) -> 1.0068942 | V55: =V54*U54*H54/H55 -> 1.3304835 | W55: =(($M175/$M55)^(1/10)-1) -> 0.09169518 | X55: =(($V175/$V55)^(1/10)-1) -> 0.087974152 | Y55: =W55-X55 -> 0.003721028
A56: 1874.11 | B56: =VALUE(LEFT(A56, 4)) -> 1874 | C56: 11 | D56: =DATE(B56, VALUE(C56), 1) -> 684771 | E56: 4.57 | F56: 0.33 | G56: 0.46 | H56: 11.512651 | I56: =I55+1/12 -> 1874.875 | J56: =J46*2/12+J58*10/12 -> 5.1366667 | K56: =E56*$H$1851/H56 -> 124.82635 | L56: =F56*$H$1851/H56 -> 9.0137187 | M56: =M55*((K56+(L56/12))/K55) -> 158.46144 | N56: =G56*$H$1851/H56 -> 12.564578 | O56: =N56*(M56/K56) -> 15.950167 | P56: NA | R56: NA | U56: =((J56/J57+J56/1200+((1+J57/1200)^(-119))*(1-J56/J57))) -> 1.0068704 | V56: =V55*U55*H55/H56 -> 1.3507205 | W56: =(($M176/$M56)^(1/10)-1) -> 0.090050903 | X56: =(($V176/$V56)^(1/10)-1) -> 0.08917331 | Y56: =W56-X56 -> 0.00087759235
A57: 1874.12 | B57: =VALUE(LEFT(A57, 4)) -> 1874 | C57: 12 | D57: =DATE(B57, VALUE(C57), 1) -> 684801 | E57: 4.54 | F57: 0.33 | G57: 0.46 | H57: 11.512651 | I57: =I56+1/12 -> 1874.9583 | J57: =J46*1/12+J58*11/12 -> 5.1033333 | K57: =E57*$H$1851/H57 -> 124.00692 | L57: =F57*$H$1851/H57 -> 9.0137187 | M57: =M56*((K57+(L57/12))/K56) -> 158.37475 | N57: =G57*$H$1851/H57 -> 12.564578 | O57: =N57*(M57/K57) -> 16.046781 | P57: NA | R57: NA | U57: =((J57/J58+J57/1200+((1+J58/1200)^(-119))*(1-J57/J58))) -> 1.0068465 | V57: =V56*U56*H56/H57 -> 1.3600004 | W57: =(($M177/$M57)^(1/10)-1) -> 0.091753961 | X57: =(($V177/$V57)^(1/10)-1) -> 0.090069111 | Y57: =W57-X57 -> 0.0016848501
A58: 1875.01 | B58: =VALUE(LEFT(A58, 4)) -> 1875 | C58: 1 | D58: =DATE(B58, VALUE(C58), 1) -> 684832 | E58: 4.54 | F58: 0.3275 | G58: 0.4517 | H58: 11.512651 | I58: =I57+1/12 -> 1875.0417 | J58: 5.07 | K58: =E58*$H$1851/H58 -> 124.00692 | L58: =F58*$H$1851/H58 -> 8.945433 | M58: =M57*((K58+(L58/12))/K57) -> 159.3268 | N58: =G58*$H$1851/H58 -> 12.337869 | O58: =N58*(M58/K58) -> 15.851964 | P58: NA | R58: NA | U58: =((J58/J59+J58/1200+((1+J59/1200)^(-119))*(1-J58/J59))) -> 1.0073432 | V58: =V57*U57*H57/H58 -> 1.3693117 | W58: =(($M178/$M58)^(1/10)-1) -> 0.089208398 | X58: =(($V178/$V58)^(1/10)-1) -> 0.089721129 | Y58: =W58-X58 -> -0.00051273101
A59: 1875.02 | B59: =VALUE(LEFT(A59, 4)) -> 1875 | C59: 2 | D59: =DATE(B59, VALUE(C59), 1) -> 684863 | E59: 4.53 | F59: 0.325 | G59: 0.4433 | H59: 11.512651 | I59: =I58+1/12 -> 1875.125 | J59: =J58*11/12+J70*1/12 -> 5.03 | K59: =E59*$H$1851/H59 -> 123.73378 | L59: =F59*$H$1851/H59 -> 8.8771472 | M59: =M58*((K59+(L59/12))/K58) -> 159.92632 | N59: =G59*$H$1851/H59 -> 12.108429 | O59: =N59*(M59/K59) -> 15.650185 | P59: NA | R59: NA | U59: =((J59/J60+J59/1200+((1+J60/1200)^(-119))*(1-J59/J60))) -> 1.0073156 | V59: =V58*U58*H58/H59 -> 1.3793668 | W59: =(($M179/$M59)^(1/10)-1) -> 0.091463781 | X59: =(($V179/$V59)^(1/10)-1) -> 0.088112117 | Y59: =W59-X59 -> 0.0033516631
A60: 1875.03 | B60: =VALUE(LEFT(A60, 4)) -> 1875 | C60: 3 | D60: =DATE(B60, VALUE(C60), 1) -> 684891 | E60: 4.59 | F60: 0.3225 | G60: 0.435 | H60: 11.512651 | I60: =I59+1/12 -> 1875.2083 | J60: =J58*10/12+J70*2/12 -> 4.99 | K60: =E60*$H$1851/H60 -> 125.37263 | L60: =F60*$H$1851/H60 -> 8.8088615 | M60: =M59*((K60+(L60/12))/K59) -> 162.99334 | N60: =G60*$H$1851/H60 -> 11.88172 | O60: =N60*(M60/K60) -> 15.447082 | P60: NA | R60: NA | U60: =((J60/J61+J60/1200+((1+J61/1200)^(-119))*(1-J60/J61))) -> 1.007288 | V60: =V59*U59*H59/H60 -> 1.3894577 | W60: =(($M180/$M60)^(1/10)-1) -> 0.092756125 | X60: =(($V180/$V60)^(1/10)-1) -> 0.090254177 | Y60: =W60-X60 -> 0.0025019482
A61: 1875.04 | B61: =VALUE(LEFT(A61, 4)) -> 1875 | C61: 4 | D61: =DATE(B61, VALUE(C61), 1) -> 684922 | E61: 4.65 | F61: 0.32 | G61: 0.4267 | H61: 11.607736 | I61: =I60+1/12 -> 1875.2917 | J61: =J58*9/12+J70*3/12 -> 4.95 | K61: =E61*$H$1851/H61 -> 125.97108 | L61: =F61*$H$1851/H61 -> 8.6689777 | M61: =M60*((K61+(L61/12))/K60) -> 164.71056 | N61: =G61*$H$1851/H61 -> 11.55954 | O61: =N61*(M61/K61) -> 15.114408 | P61: NA | R61: NA | U61: =((J61/J62+J61/1200+((1+J62/1200)^(-119))*(1-J61/J62))) -> 1.0072604 | V61: =V60*U60*H60/H61 -> 1.3881193 | W61: =(($M181/$M61)^(1/10)-1) -> 0.090695275 | X61: =(($V181/$V61)^(1/10)-1) -> 0.089529623 | Y61: =W61-X61 -> 0.0011656519
A62: 1875.05 | B62: =VALUE(LEFT(A62, 4)) -> 1875 | C62: 5 | D62: =DATE(B62, VALUE(C62), 1) -> 684952 | E62: 4.47 | F62: 0.3175 | G62: 0.4183 | H62: 11.322321 | I62: =I61+1/12 -> 1875.375 | J62: =J58*8/12+J70*4/12 -> 4.91 | K62: =E62*$H$1851/H62 -> 124.14736 | L62: =F62*$H$1851/H62 -> 8.818073 | M62: =M61*((K62+(L62/12))/K61) -> 163.28682 | N62: =G62*$H$1851/H62 -> 11.617638 | O62: =N62*(M62/K62) -> 15.280285 | P62: NA | R62: NA | U62: =((J62/J63+J62/1200+((1+J63/1200)^(-119))*(1-J62/J63))) -> 1.0072328 | V62: =V61*U61*H61/H62 -> 1.4334436 | W62: =(($M182/$M62)^(1/10)-1) -> 0.093516579 | X62: =(($V182/$V62)^(1/10)-1) -> 0.088992587 | Y62: =W62-X62 -> 0.0045239922
A63: 1875.06 | B63: =VALUE(LEFT(A63, 4)) -> 1875 | C63: 6 | D63: =DATE(B63, VALUE(C63), 1) -> 684983 | E63: 4.38 | F63: 0.315 | G63: 0.41 | H63: 11.132071 | I63: =I62+1/12 -> 1875.4583 | J63: =J58*7/12+J70*5/12 -> 4.87 | K63: =E63*$H$1851/H63 -> 123.72673 | L63: =F63*$H$1851/H63 -> 8.8981556 | M63: =M62*((K63+(L63/12))/K62) -> 163.70887 | N63: =G63*$H$1851/H63 -> 11.581726 | O63: =N63*(M63/K63) -> 15.324346 | P63: NA | R63: NA | U63: =((J63/J64+J63/1200+((1+J64/1200)^(-119))*(1-J63/J64))) -> 1.0072052 | V63: =V62*U62*H62/H63 -> 1.4684864 | W63: =(($M183/$M63)^(1/10)-1) -> 0.095914444 | X63: =(($V183/$V63)^(1/10)-1) -> 0.089383604 | Y63: =W63-X63 -> 0.00653084
A64: 1875.07 | B64: =VALUE(LEFT(A64, 4)) -> 1875 | C64: 7 | D64: =DATE(B64, VALUE(C64), 1) -> 685013 | E64: 4.39 | F64: 0.3125 | G64: 0.4017 | H64: 11.132071 | I64: =I63+1/12 -> 1875.5417 | J64: =J58*6/12+J70*6/12 -> 4.83 | K64: =E64*$H$1851/H64 -> 124.00922 | L64: =F64*$H$1851/H64 -> 8.8275353 | M64: =M63*((K64+(L64/12))/K63) -> 165.05598 | N64: =G64*$H$1851/H64 -> 11.347267 | O64: =N64*(M64/K64) -> 15.103186 | P64: NA | R64: NA | U64: =((J64/J65+J64/1200+((1+J65/1200)^(-119))*(1-J64/J65))) -> 1.0071777 | V64: =V63*U63*H63/H64 -> 1.4790672 | W64: =(($M184/$M64)^(1/10)-1) -> 0.09826006 | X64: =(($V184/$V64)^(1/10)-1) -> 0.087725445 | Y64: =W64-X64 -> 0.010534615
A65: 1875.08 | B65: =VALUE(LEFT(A65, 4)) -> 1875 | C65: 8 | D65: =DATE(B65, VALUE(C65), 1) -> 685044 | E65: 4.41 | F65: 0.31 | G65: 0.3933 | H65: 11.227155 | I65: =I64+1/12 -> 1875.625 | J65: =J58*5/12+J70*7/12 -> 4.79 | K65: =E65*$H$1851/H65 -> 123.51914 | L65: =F65*$H$1851/H65 -> 8.6827515 | M65: =M64*((K65+(L65/12))/K64) -> 165.36675 | N65: =G65*$H$1851/H65 -> 11.015891 | O65: =N65*(M65/K65) -> 14.748015 | P65: NA | R65: NA | U65: =((J65/J66+J65/1200+((1+J66/1200)^(-119))*(1-J65/J66))) -> 1.0071501 | V65: =V64*U64*H64/H65 -> 1.4770671 | W65: =(($M185/$M65)^(1/10)-1) -> 0.10457179 | X65: =(($V185/$V65)^(1/10)-1) -> 0.088298362 | Y65: =W65-X65 -> 0.016273431
A66: 1875.09 | B66: =VALUE(LEFT(A66, 4)) -> 1875 | C66: 9 | D66: =DATE(B66, VALUE(C66), 1) -> 685075 | E66: 4.37 | F66: 0.3075 | G66: 0.385 | H66: 11.132071 | I66: =I65+1/12 -> 1875.7083 | J66: =J58*4/12+J70*8/12 -> 4.75 | K66: =E66*$H$1851/H66 -> 123.44425 | L66: =F66*$H$1851/H66 -> 8.6862947 | M66: =M65*((K66+(L66/12))/K65) -> 166.23559 | N66: =G66*$H$1851/H66 -> 10.875523 | O66: =N66*(M66/K66) -> 14.64547 | P66: NA | R66: NA | U66: =((J66/J67+J66/1200+((1+J67/1200)^(-119))*(1-J66/J67))) -> 1.0071226 | V66: =V65*U65*H65/H66 -> 1.5003349 | W66: =(($M186/$M66)^(1/10)-1) -> 0.10440819 | X66: =(($V186/$V66)^(1/10)-1) -> 0.088325407 | Y66: =W66-X66 -> 0.016082784
A67: 1875.1 | B67: =VALUE(LEFT(A67, 4)) -> 1875 | C67: 10 | D67: =DATE(B67, VALUE(C67), 1) -> 685105 | E67: 4.3 | F67: 0.305 | G67: 0.3767 | H67: 11.132071 | I67: =I66+1/12 -> 1875.7917 | J67: =J58*3/12+J70*9/12 -> 4.71 | K67: =E67*$H$1851/H67 -> 121.46689 | L67: =F67*$H$1851/H67 -> 8.6156744 | M67: =M66*((K67+(L67/12))/K66) -> 164.53963 | N67: =G67*$H$1851/H67 -> 10.641064 | O67: =N67*(M67/K67) -> 14.414437 | P67: NA | R67: NA | U67: =((J67/J68+J67/1200+((1+J68/1200)^(-119))*(1-J67/J68))) -> 1.0070951 | V67: =V66*U66*H66/H67 -> 1.5110212 | W67: =(($M187/$M67)^(1/10)-1) -> 0.11227183 | X67: =(($V187/$V67)^(1/10)-1) -> 0.087976728 | Y67: =W67-X67 -> 0.024295103
A68: 1875.11 | B68: =VALUE(LEFT(A68, 4)) -> 1875 | C68: 11 | D68: =DATE(B68, VALUE(C68), 1) -> 685136 | E68: 4.37 | F68: 0.3025 | G68: 0.3683 | H68: 11.036906 | I68: =I67+1/12 -> 1875.875 | J68: =J58*2/12+J70*10/12 -> 4.67 | K68: =E68*$H$1851/H68 -> 124.50865 | L68: =F68*$H$1851/H68 -> 8.6187335 | M68: =M67*((K68+(L68/12))/K67) -> 169.63293 | N68: =G68*$H$1851/H68 -> 10.493486 | O68: =N68*(M68/K68) -> 14.296524 | P68: NA | R68: NA | U68: =((J68/J69+J68/1200+((1+J69/1200)^(-119))*(1-J68/J69))) -> 1.0070676 | V68: =V67*U67*H67/H68 -> 1.5348632 | W68: =(($M188/$M68)^(1/10)-1) -> 0.11499504 | X68: =(($V188/$V68)^(1/10)-1) -> 0.085396079 | Y68: =W68-X68 -> 0.029598959
A69: 1875.12 | B69: =VALUE(LEFT(A69, 4)) -> 1875 | C69: 12 | D69: =DATE(B69, VALUE(C69), 1) -> 685166 | E69: 4.37 | F69: 0.3 | G69: 0.36 | H69: 10.94174 | I69: =I68+1/12 -> 1875.9583 | J69: =J58*1/12+J70*11/12 -> 4.63 | K69: =E69*$H$1851/H69 -> 125.59155 | L69: =F69*$H$1851/H69 -> 8.6218459 | M69: =M68*((K69+(L69/12))/K68) -> 172.08719 | N69: =G69*$H$1851/H69 -> 10.346215 | O69: =N69*(M69/K69) -> 14.176519 | P69: NA | R69: NA | U69: =((J69/J70+J69/1200+((1+J70/1200)^(-119))*(1-J69/J70))) -> 1.0070401 | V69: =V68*U68*H68/H69 -> 1.5591548 | W69: =(($M189/$M69)^(1/10)-1) -> 0.11035321 | X69: =(($V189/$V69)^(1/10)-1) -> 0.081565063 | Y69: =W69-X69 -> 0.028788146
A70: 1876.01 | B70: =VALUE(LEFT(A70, 4)) -> 1876 | C70: 1 | D70: =DATE(B70, VALUE(C70), 1) -> 685197 | E70: 4.46 | F70: 0.3 | G70: 0.3533 | H70: 10.846575 | I70: =I69+1/12 -> 1876.0417 | J70: 4.59 | K70: =E70*$H$1851/H70 -> 129.30271 | L70: =F70*$H$1851/H70 -> 8.6974919 | M70: =M69*((K70+(L70/12))/K69) -> 178.16538 | N70: =G70*$H$1851/H70 -> 10.242746 | O70: =N70*(M70/K70) -> 14.113415 | P70: NA | R70: NA | U70: =((J70/J71+J70/1200+((1+J71/1200)^(-119))*(1-J70/J71))) -> 1.0047535 | V70: =V69*U69*H69/H70 -> 1.5839074 | W70: =(($M190/$M70)^(1/10)-1) -> 0.10953518 | X70: =(($V190/$V70)^(1/10)-1) -> 0.08282497 | Y70: =W70-X70 -> 0.026710212
A71: 1876.02 | B71: =VALUE(LEFT(A71, 4)) -> 1876 | C71: 2 | D71: =DATE(B71, VALUE(C71), 1) -> 685228 | E71: 4.52 | F71: 0.3 | G71: 0.3467 | H71: 10.846575 | I71: =I70+1/12 -> 1876.125 | J71: =J70*11/12+J82*1/12 -> 4.5783333 | K71: =E71*$H$1851/H71 -> 131.04221 | L71: =F71*$H$1851/H71 -> 8.6974919 | M71: =M70*((K71+(L71/12))/K70) -> 181.56091 | N71: =G71*$H$1851/H71 -> 10.051401 | O71: =N71*(M71/K71) -> 13.926365 | P71: NA | R71: NA | U71: =((J71/J72+J71/1200+((1+J72/1200)^(-119))*(1-J71/J72))) -> 1.0047443 | V71: =V70*U70*H70/H71 -> 1.5914365 | W71: =(($M191/$M71)^(1/10)-1) -> 0.10996621 | X71: =(($V191/$V71)^(1/10)-1) -> 0.082501543 | Y71: =W71-X71 -> 0.027464669
A72: 1876.03 | B72: =VALUE(LEFT(A72, 4)) -> 1876 | C72: 3 | D72: =DATE(B72, VALUE(C72), 1) -> 685257 | E72: 4.51 | F72: 0.3 | G72: 0.34 | H72: 10.846575 | I72: =I71+1/12 -> 1876.2083 | J72: =J70*10/12+J82*2/12 -> 4.5666667 | K72: =E72*$H$1851/H72 -> 130.75229 | L72: =F72*$H$1851/H72 -> 8.6974919 | M72: =M71*((K72+(L72/12))/K71) -> 182.16344 | N72: =G72*$H$1851/H72 -> 9.8571575 | O72: =N72*(M72/K72) -> 13.732942 | P72: NA | R72: NA | U72: =((J72/J73+J72/1200+((1+J73/1200)^(-119))*(1-J72/J73))) -> 1.0047351 | V72: =V71*U71*H71/H72 -> 1.5989868 | W72: =(($M192/$M72)^(1/10)-1) -> 0.10901821 | X72: =(($V192/$V72)^(1/10)-1) -> 0.083477151 | Y72: =W72-X72 -> 0.025541063
A73: 1876.04 | B73: =VALUE(LEFT(A73, 4)) -> 1876 | C73: 4 | D73: =DATE(B73, VALUE(C73), 1) -> 685288 | E73: 4.34 | F73: 0.3 | G73: 0.3333 | H73: 10.751491 | I73: =I72+1/12 -> 1876.2917 | J73: =J70*9/12+J82*3/12 -> 4.555 | K73: =E73*$H$1851/H73 -> 126.93648 | L73: =F73*$H$1851/H73 -> 8.774411 | M73: =M72*((K73+(L73/12))/K72) -> 177.86597 | N73: =G73*$H$1851/H73 -> 9.7483706 | O73: =N73*(M73/K73) -> 13.659614 | P73: NA | R73: NA | U73: =((J73/J74+J73/1200+((1+J74/1200)^(-119))*(1-J73/J74))) -> 1.0047259 | V73: =V72*U72*H72/H73 -> 1.6207662 | W73: =(($M193/$M73)^(1/10)-1) -> 0.11192838 | X73: =(($V193/$V73)^(1/10)-1) -> 0.083517231 | Y73: =W73-X73 -> 0.028411151
A74: 1876.05 | B74: =VALUE(LEFT(A74, 4)) -> 1876 | C74: 5 | D74: =DATE(B74, VALUE(C74), 1) -> 685318 | E74: 4.18 | F74: 0.3 | G74: 0.3267 | H74: 10.370911 | I74: =I73+1/12 -> 1876.375 | J74: =J70*8/12+J82*4/12 -> 4.5433333 | K74: =E74*$H$1851/H74 -> 126.74324 | L74: =F74*$H$1851/H74 -> 9.0964046 | M74: =M73*((K74+(L74/12))/K73) -> 178.65736 | N74: =G74*$H$1851/H74 -> 9.9059846 | O74: =N74*(M74/K74) -> 13.963483 | P74: NA | R74: NA | U74: =((J74/J75+J74/1200+((1+J75/1200)^(-119))*(1-J74/J75))) -> 1.0047166 | V74: =V73*U73*H73/H74 -> 1.6881839 | W74: =(($M194/$M74)^(1/10)-1) -> 0.1124141 | X74: =(($V194/$V74)^(1/10)-1) -> 0.081971735 | Y74: =W74-X74 -> 0.030442368
A75: 1876.06 | B75: =VALUE(LEFT(A75, 4)) -> 1876 | C75: 6 | D75: =DATE(B75, VALUE(C75), 1) -> 685349 | E75: 4.15 | F75: 0.3 | G75: 0.32 | H75: 10.085415 | I75: =I74+1/12 -> 1876.4583 | J75: =J70*7/12+J82*5/12 -> 4.5316667 | K75: =E75*$H$1851/H75 -> 129.39567 | L75: =F75*$H$1851/H75 -> 9.3539037 | M75: =M74*((K75+(L75/12))/K74) -> 183.495 | N75: =G75*$H$1851/H75 -> 9.9774973 | O75: =N75*(M75/K75) -> 14.149012 | P75: NA | R75: NA | U75: =((J75/J76+J75/1200+((1+J76/1200)^(-119))*(1-J75/J76))) -> 1.0047074 | V75: =V74*U74*H74/H75 -> 1.7441606 | W75: =(($M195/$M75)^(1/10)-1) -> 0.11623667 | X75: =(($V195/$V75)^(1/10)-1) -> 0.079999818 | Y75: =W75-X75 -> 0.03623685
A76: 1876.07 | B76: =VALUE(LEFT(A76, 4)) -> 1876 | C76: 7 | D76: =DATE(B76, VALUE(C76), 1) -> 685379 | E76: 4.1 | F76: 0.3 | G76: 0.3133 | H76: 10.085415 | I76: =I75+1/12 -> 1876.5417 | J76: =J70*6/12+J82*6/12 -> 4.52 | K76: =E76*$H$1851/H76 -> 127.83668 | L76: =F76*$H$1851/H76 -> 9.3539037 | M76: =M75*((K76+(L76/12))/K75) -> 182.38961 | N76: =G76*$H$1851/H76 -> 9.7685935 | O76: =N76*(M76/K76) -> 13.937236 | P76: NA | R76: NA | U76: =((J76/J77+J76/1200+((1+J77/1200)^(-119))*(1-J76/J77))) -> 1.0046982 | V76: =V75*U75*H75/H76 -> 1.7523711 | W76: =(($M196/$M76)^(1/10)-1) -> 0.11759364 | X76: =(($V196/$V76)^(1/10)-1) -> 0.078330824 | Y76: =W76-X76 -> 0.039262817
A77: 1876.08 | B77: =VALUE(LEFT(A77, 4)) -> 1876 | C77: 8 | D77: =DATE(B77, VALUE(C77), 1) -> 685410 | E77: 3.93 | F77: 0.3 | G77: 0.3067 | H77: 10.18058 | I77: =I76+1/12 -> 1876.625 | J77: =J70*5/12+J82*7/12 -> 4.5083333 | K77: =E77*$H$1851/H77 -> 121.3907 | L77: =F77*$H$1851/H77 -> 9.266466 | M77: =M76*((K77+(L77/12))/K76) -> 174.29462 | N77: =G77*$H$1851/H77 -> 9.4734171 | O77: =N77*(M77/K77) -> 13.602076 | P77: NA | R77: NA | U77: =((J77/J78+J77/1200+((1+J78/1200)^(-119))*(1-J77/J78))) -> 1.004689 | V77: =V76*U76*H76/H77 -> 1.7441464 | W77: =(($M197/$M77)^(1/10)-1) -> 0.12251792 | X77: =(($V197/$V77)^(1/10)-1) -> 0.077695185 | Y77: =W77-X77 -> 0.044822734
A78: 1876.09 | B78: =VALUE(LEFT(A78, 4)) -> 1876 | C78: 9 | D78: =DATE(B78, VALUE(C78), 1) -> 685441 | E78: 3.69 | F78: 0.3 | G78: 0.3 | H78: 10.275745 | I78: =I77+1/12 -> 1876.7083 | J78: =J70*4/12+J82*8/12 -> 4.4966667 | K78: =E78*$H$1851/H78 -> 112.92197 | L78: =F78*$H$1851/H78 -> 9.1806478 | M78: =M77*((K78+(L78/12))/K77) -> 163.23355 | N78: =G78*$H$1851/H78 -> 9.1806478 | O78: =N78*(M78/K78) -> 13.271021 | P78: NA | R78: NA | U78: =((J78/J79+J78/1200+((1+J79/1200)^(-119))*(1-J78/J79))) -> 1.0046798 | V78: =V77*U77*H77/H78 -> 1.7360962 | W78: =(($M198/$M78)^(1/10)-1) -> 0.13319853 | X78: =(($V198/$V78)^(1/10)-1) -> 0.078391421 | Y78: =W78-X78 -> 0.054807111
A79: 1876.1 | B79: =VALUE(LEFT(A79, 4)) -> 1876 | C79: 10 | D79: =DATE(B79, VALUE(C79), 1) -> 685471 | E79: 3.67 | F79: 0.3 | G79: 0.2933 | H79: 10.465995 | I79: =I78+1/12 -> 1876.7917 | J79: =J70*3/12+J82*9/12 -> 4.485 | K79: =E79*$H$1851/H79 -> 110.26837 | L79: =F79*$H$1851/H79 -> 9.0137631 | M79: =M78*((K79+(L79/12))/K78) -> 160.48348 | N79: =G79*$H$1851/H79 -> 8.8124557 | O79: =N79*(M79/K79) -> 12.82556 | P79: NA | R79: NA | U79: =((J79/J80+J79/1200+((1+J80/1200)^(-119))*(1-J79/J80))) -> 1.0046705 | V79: =V78*U78*H78/H79 -> 1.7125144 | W79: =(($M199/$M79)^(1/10)-1) -> 0.13835154 | X79: =(($V199/$V79)^(1/10)-1) -> 0.080066312 | Y79: =W79-X79 -> 0.058285228
A80: 1876.11 | B80: =VALUE(LEFT(A80, 4)) -> 1876 | C80: 11 | D80: =DATE(B80, VALUE(C80), 1) -> 685502 | E80: 3.6 | F80: 0.3 | G80: 0.2867 | H80: 10.56116 | I80: =I79+1/12 -> 1876.875 | J80: =J70*2/12+J82*10/12 -> 4.4733333 | K80: =E80*$H$1851/H80 -> 107.19049 | L80: =F80*$H$1851/H80 -> 8.9325412 | M80: =M79*((K80+(L80/12))/K79) -> 157.08733 | N80: =G80*$H$1851/H80 -> 8.5365319 | O80: =N80*(M80/K80) -> 12.51026 | P80: NA | R80: NA | U80: =((J80/J81+J80/1200+((1+J81/1200)^(-119))*(1-J80/J81))) -> 1.0046613 | V80: =V79*U79*H79/H80 -> 1.7050095 | W80: =(($M200/$M80)^(1/10)-1) -> 0.14394905 | X80: =(($V200/$V80)^(1/10)-1) -> 0.080741145 | Y80: =W80-X80 -> 0.06320791
A81: 1876.12 | B81: =VALUE(LEFT(A81, 4)) -> 1876 | C81: 12 | D81: =DATE(B81, VALUE(C81), 1) -> 685532 | E81: 3.58 | F81: 0.3 | G81: 0.28 | H81: 10.751491 | I81: =I80+1/12 -> 1876.9583 | J81: =J70*1/12+J82*11/12 -> 4.4616667 | K81: =E81*$H$1851/H81 -> 104.70797 | L81: =F81*$H$1851/H81 -> 8.774411 | M81: =M80*((K81+(L81/12))/K80) -> 154.52077 | N81: =G81*$H$1851/H81 -> 8.1894503 | O81: =N81*(M81/K81) -> 12.085424 | P81: NA | R81: NA | U81: =((J81/J82+J81/1200+((1+J82/1200)^(-119))*(1-J81/J82))) -> 1.0046521 | V81: =V80*U80*H80/H81 -> 1.6826331 | W81: =(($M201/$M81)^(1/10)-1) -> 0.14180044 | X81: =(($V201/$V81)^(1/10)-1) -> 0.08104437 | Y81: =W81-X81 -> 0.06075607
A82: 1877.01 | B82: =VALUE(LEFT(A82, 4)) -> 1877 | C82: 1 | D82: =DATE(B82, VALUE(C82), 1) -> 685563 | E82: 3.55 | F82: 0.2908 | G82: 0.2817 | H82: 10.94174 | I82: =I81+1/12 -> 1877.0417 | J82: 4.45 | K82: =E82*$H$1851/H82 -> 102.02518 | L82: =F82*$H$1851/H82 -> 8.3574426 | M82: =M81*((K82+(L82/12))/K81) -> 151.58947 | N82: =G82*$H$1851/H82 -> 8.0959133 | O82: =N82*(M82/K82) -> 12.028944 | P82: NA | R82: NA | U82: =((J82/J83+J82/1200+((1+J83/1200)^(-119))*(1-J82/J83))) -> 1.0044425 | V82: =V81*U81*H81/H82 -> 1.6610679 | W82: =(($M202/$M82)^(1/10)-1) -> 0.14039429 | X82: =(($V202/$V82)^(1/10)-1) -> 0.08003707 | Y82: =W82-X82 -> 0.060357221
A83: 1877.02 | B83: =VALUE(LEFT(A83, 4)) -> 1877 | C83: 2 | D83: =DATE(B83, VALUE(C83), 1) -> 685594 | E83: 3.34 | F83: 0.2817 | G83: 0.2833 | H83: 10.656326 | I83: =I82+1/12 -> 1877.125 | J83: =J82*11/12+J94*1/12 -> 4.4408333 | K83: =E83*$H$1851/H83 -> 98.56084 | L83: =F83*$H$1851/H83 -> 8.3127511 | M83: =M82*((K83+(L83/12))/K82) -> 147.4714 | N83: =G83*$H$1851/H83 -> 8.3599658 | O83: =N83*(M83/K83) -> 12.508577 | P83: NA | R83: NA | U83: =((J83/J84+J83/1200+((1+J84/1200)^(-119))*(1-J83/J84))) -> 1.0044352 | V83: =V82*U82*H82/H83 -> 1.7131343 | W83: =(($M203/$M83)^(1/10)-1) -> 0.14175118 | X83: =(($V203/$V83)^(1/10)-1) -> 0.075638237 | Y83: =W83-X83 -> 0.066112941
A84: 1877.03 | B84: =VALUE(LEFT(A84, 4)) -> 1877 | C84: 3 | D84: =DATE(B84, VALUE(C84), 1) -> 685622 | E84: 3.17 | F84: 0.2725 | G84: 0.285 | H84: 10.18058 | I84: =I83+1/12 -> 1877.2083 | J84: =J82*10/12+J94*2/12 -> 4.4316667 | K84: =E84*$H$1851/H84 -> 97.915657 | L84: =F84*$H$1851/H84 -> 8.4170399 | M84: =M83*((K84+(L84/12))/K83) -> 147.55555 | N84: =G84*$H$1851/H84 -> 8.8031427 | O84: =N84*(M84/K84) -> 13.266035 | P84: NA | R84: NA | U84: =((J84/J85+J84/1200+((1+J85/1200)^(-119))*(1-J84/J85))) -> 1.0044279 | V84: =V83*U83*H83/H84 -> 1.8011434 | W84: =(($M204/$M84)^(1/10)-1) -> 0.14471927 | X84: =(($V204/$V84)^(1/10)-1) -> 0.070466246 | Y84: =W84-X84 -> 0.074253024
A85: 1877.04 | B85: =VALUE(LEFT(A85, 4)) -> 1877 | C85: 4 | D85: =DATE(B85, VALUE(C85), 1) -> 685653 | E85: 2.94 | F85: 0.2633 | G85: 0.2867 | H85: 10.465995 | I85: =I84+1/12 -> 1877.2917 | J85: =J82*9/12+J94*3/12 -> 4.4225 | K85: =E85*$H$1851/H85 -> 88.334878 | L85: =F85*$H$1851/H85 -> 7.9110794 | M85: =M84*((K85+(L85/12))/K84) -> 134.11112 | N85: =G85*$H$1851/H85 -> 8.6141529 | O85: =N85*(M85/K85) -> 13.078115 | P85: NA | R85: NA | U85: =((J85/J86+J85/1200+((1+J86/1200)^(-119))*(1-J85/J86))) -> 1.0044206 | V85: =V84*U84*H84/H85 -> 1.7597828 | W85: =(($M205/$M85)^(1/10)-1) -> 0.1587129 | X85: =(($V205/$V85)^(1/10)-1) -> 0.073160831 | Y85: =W85-X85 -> 0.085552073
A86: 1877.05 | B86: =VALUE(LEFT(A86, 4)) -> 1877 | C86: 5 | D86: =DATE(B86, VALUE(C86), 1) -> 685683 | E86: 2.94 | F86: 0.2542 | G86: 0.2883 | H86: 10.656326 | I86: =I85+1/12 -> 1877.375 | J86: =J82*8/12+J94*4/12 -> 4.4133333 | K86: =E86*$H$1851/H86 -> 86.757146 | L86: =F86*$H$1851/H86 -> 7.5012471 | M86: =M85*((K86+(L86/12))/K85) -> 132.66482 | N86: =G86*$H$1851/H86 -> 8.507512 | O86: =N86*(M86/K86) -> 13.009275 | P86: NA | R86: NA | U86: =((J86/J87+J86/1200+((1+J87/1200)^(-119))*(1-J86/J87))) -> 1.0044132 | V86: =V85*U85*H85/H86 -> 1.7359919 | W86: =(($M206/$M86)^(1/10)-1) -> 0.16233557 | X86: =(($V206/$V86)^(1/10)-1) -> 0.07482891 | Y86: =W86-X86 -> 0.087506661
A87: 1877.06 | B87: =VALUE(LEFT(A87, 4)) -> 1877 | C87: 6 | D87: =DATE(B87, VALUE(C87), 1) -> 685714 | E87: 2.73 | F87: 0.245 | G87: 0.29 | H87: 10.085415 | I87: =I86+1/12 -> 1877.4583 | J87: =J82*7/12+J94*5/12 -> 4.4041667 | K87: =E87*$H$1851/H87 -> 85.120524 | L87: =F87*$H$1851/H87 -> 7.6390214 | M87: =M86*((K87+(L87/12))/K86) -> 131.13562 | N87: =G87*$H$1851/H87 -> 9.042107 | O87: =N87*(M87/K87) -> 13.930157 | P87: NA | R87: NA | U87: =((J87/J88+J87/1200+((1+J88/1200)^(-119))*(1-J87/J88))) -> 1.0044059 | V87: =V86*U86*H86/H87 -> 1.8423571 | W87: =(($M207/$M87)^(1/10)-1) -> 0.16205708 | X87: =(($V207/$V87)^(1/10)-1) -> 0.069928056 | Y87: =W87-X87 -> 0.092129021
A88: 1877.07 | B88: =VALUE(LEFT(A88, 4)) -> 1877 | C88: 7 | D88: =DATE(B88, VALUE(C88), 1) -> 685744 | E88: 2.85 | F88: 0.2358 | G88: 0.2917 | H88: 10.18058 | I88: =I87+1/12 -> 1877.5417 | J88: =J82*6/12+J94*6/12 -> 4.395 | K88: =E88*$H$1851/H88 -> 88.031427 | L88: =F88*$H$1851/H88 -> 7.2834423 | M88: =M87*((K88+(L88/12))/K87) -> 136.55518 | N88: =G88*$H$1851/H88 -> 9.0100938 | O88: =N88*(M88/K88) -> 13.976543 | P88: NA | R88: NA | U88: =((J88/J89+J88/1200+((1+J89/1200)^(-119))*(1-J88/J89))) -> 1.0043986 | V88: =V87*U87*H87/H88 -> 1.8331767 | W88: =(($M208/$M88)^(1/10)-1) -> 0.15629331 | X88: =(($V208/$V88)^(1/10)-1) -> 0.071953548 | Y88: =W88-X88 -> 0.084339761
A89: 1877.08 | B89: =VALUE(LEFT(A89, 4)) -> 1877 | C89: 8 | D89: =DATE(B89, VALUE(C89), 1) -> 685775 | E89: 3.05 | F89: 0.2267 | G89: 0.2933 | H89: 9.8 | I89: =I88+1/12 -> 1877.625 | J89: =J82*5/12+J94*7/12 -> 4.3858333 | K89: =E89*$H$1851/H89 -> 97.867653 | L89: =F89*$H$1851/H89 -> 7.2742941 | M89: =M88*((K89+(L89/12))/K88) -> 152.75356 | N89: =G89*$H$1851/H89 -> 9.4113386 | O89: =N89*(M89/K89) -> 14.689383 | P89: NA | R89: NA | U89: =((J89/J90+J89/1200+((1+J90/1200)^(-119))*(1-J89/J90))) -> 1.0043912 | V89: =V88*U88*H88/H89 -> 1.912744 | W89: =(($M209/$M89)^(1/10)-1) -> 0.13955989 | X89: =(($V209/$V89)^(1/10)-1) -> 0.066339364 | Y89: =W89-X89 -> 0.073220527
A90: 1877.09 | B90: =VALUE(LEFT(A90, 4)) -> 1877 | C90: 9 | D90: =DATE(B90, VALUE(C90), 1) -> 685806 | E90: 3.24 | F90: 0.2175 | G90: 0.295 | H90: 9.7048347 | I90: =I89+1/12 -> 1877.7083 | J90: =J82*4/12+J94*8/12 -> 4.3766667 | K90: =E90*$H$1851/H90 -> 104.9838 | L90: =F90*$H$1851/H90 -> 7.0475234 | M90: =M89*((K90+(L90/12))/K89) -> 164.77722 | N90: =G90*$H$1851/H90 -> 9.5587099 | O90: =N90*(M90/K90) -> 15.002864 | P90: NA | R90: NA | U90: =((J90/J91+J90/1200+((1+J91/1200)^(-119))*(1-J90/J91))) -> 1.0043839 | V90: =V89*U89*H89/H90 -> 1.939982 | W90: =(($M210/$M90)^(1/10)-1) -> 0.13127468 | X90: =(($V210/$V90)^(1/10)-1) -> 0.066318029 | Y90: =W90-X90 -> 0.064956651
A91: 1877.1 | B91: =VALUE(LEFT(A91, 4)) -> 1877 | C91: 10 | D91: =DATE(B91, VALUE(C91), 1) -> 685836 | E91: 3.31 | F91: 0.2083 | G91: 0.2967 | H91: 9.7048347 | I91: =I90+1/12 -> 1877.7917 | J91: =J82*3/12+J94*9/12 -> 4.3675 | K91: =E91*$H$1851/H91 -> 107.25197 | L91: =F91*$H$1851/H91 -> 6.7494213 | M91: =M90*((K91+(L91/12))/K90) -> 169.22002 | N91: =G91*$H$1851/H91 -> 9.613794 | O91: =N91*(M91/K91) -> 15.168453 | P91: NA | R91: NA | U91: =((J91/J92+J91/1200+((1+J92/1200)^(-119))*(1-J91/J92))) -> 1.0043766 | V91: =V90*U90*H90/H91 -> 1.9484867 | W91: =(($M211/$M91)^(1/10)-1) -> 0.12353034 | X91: =(($V211/$V91)^(1/10)-1) -> 0.064786319 | Y91: =W91-X91 -> 0.058744024
A92: 1877.11 | B92: =VALUE(LEFT(A92, 4)) -> 1877 | C92: 11 | D92: =DATE(B92, VALUE(C92), 1) -> 685867 | E92: 3.26 | F92: 0.1992 | G92: 0.2983 | H92: 9.5145851 | I92: =I91+1/12 -> 1877.875 | J92: =J82*2/12+J94*10/12 -> 4.3583333 | K92: =E92*$H$1851/H92 -> 107.74401 | L92: =F92*$H$1851/H92 -> 6.583622 | M92: =M91*((K92+(L92/12))/K91) -> 170.86199 | N92: =G92*$H$1851/H92 -> 9.8589079 | O92: =N92*(M92/K92) -> 15.634396 | P92: NA | R92: NA | U92: =((J92/J93+J92/1200+((1+J93/1200)^(-119))*(1-J92/J93))) -> 1.0043693 | V92: =V91*U91*H91/H92 -> 1.9961461 | W92: =(($M212/$M92)^(1/10)-1) -> 0.12369224 | X92: =(($V212/$V92)^(1/10)-1) -> 0.061170701 | Y92: =W92-X92 -> 0.06252154
A93: 1877.12 | B93: =VALUE(LEFT(A93, 4)) -> 1877 | C93: 12 | D93: =DATE(B93, VALUE(C93), 1) -> 685897 | E93: 3.25 | F93: 0.19 | G93: 0.3 | H93: 9.5145851 | I93: =I92+1/12 -> 1877.9583 | J93: =J82*1/12+J94*11/12 -> 4.3491667 | K93: =E93*$H$1851/H93 -> 107.41351 | L93: =F93*$H$1851/H93 -> 6.2795591 | M93: =M92*((K93+(L93/12))/K92) -> 171.16772 | N93: =G93*$H$1851/H93 -> 9.9150934 | O93: =N93*(M93/K93) -> 15.800098 | P93: NA | R93: NA | U93: =((J93/J94+J93/1200+((1+J94/1200)^(-119))*(1-J93/J94))) -> 1.0043619 | V93: =V92*U92*H92/H93 -> 2.0048678 | W93: =(($M213/$M93)^(1/10)-1) -> 0.12068741 | X93: =(($V213/$V93)^(1/10)-1) -> 0.058455431 | Y93: =W93-X93 -> 0.062231978
A94: 1878.01 | B94: =VALUE(LEFT(A94, 4)) -> 1878 | C94: 1 | D94: =DATE(B94, VALUE(C94), 1) -> 685928 | E94: 3.25 | F94: 0.1892 | G94: 0.3008 | H94: 9.2290893 | I94: =I93+1/12 -> 1878.0417 | J94: 4.34 | K94: =E94*$H$1851/H94 -> 110.73628 | L94: =F94*$H$1851/H94 -> 6.4465551 | M94: =M93*((K94+(L94/12))/K93) -> 177.31876 | N94: =G94*$H$1851/H94 -> 10.249069 | O94: =N94*(M94/K94) -> 16.411533 | P94: NA | R94: NA | U94: =((J94/J95+J94/1200+((1+J95/1200)^(-119))*(1-J94/J95))) -> 1.0044217 | V94: =V93*U93*H93/H94 -> 2.0759027 | W94: =(($M214/$M94)^(1/10)-1) -> 0.11673998 | X94: =(($V214/$V94)^(1/10)-1) -> 0.053783076 | Y94: =W94-X94 -> 0.062956903
A95: 1878.02 | B95: =VALUE(LEFT(A95, 4)) -> 1878 | C95: 2 | D95: =DATE(B95, VALUE(C95), 1) -> 685959 | E95: 3.18 | F95: 0.1883 | G95: 0.3017 | H95: 9.134005 | I95: =I94+1/12 -> 1878.125 | J95: =J94*11/12+J106*1/12 -> 4.33 | K95: =E95*$H$1851/H95 -> 109.47912 | L95: =F95*$H$1851/H95 -> 6.4826785 | M95: =M94*((K95+(L95/12))/K94) -> 176.17074 | N95: =G95*$H$1851/H95 -> 10.386745 | O95: =N95*(M95/K95) -> 16.714061 | P95: NA | R95: NA | U95: =((J95/J96+J95/1200+((1+J96/1200)^(-119))*(1-J95/J96))) -> 1.0044138 | V95: =V94*U94*H94/H95 -> 2.1067873 | W95: =(($M215/$M95)^(1/10)-1) -> 0.1185446 | X95: =(($V215/$V95)^(1/10)-1) -> 0.053913136 | Y95: =W95-X95 -> 0.064631465
A96: 1878.03 | B96: =VALUE(LEFT(A96, 4)) -> 1878 | C96: 3 | D96: =DATE(B96, VALUE(C96), 1) -> 685987 | E96: 3.24 | F96: 0.1875 | G96: 0.3025 | H96: 8.9436744 | I96: =I95+1/12 -> 1878.2083 | J96: =J94*10/12+J106*2/12 -> 4.32 | K96: =E96*$H$1851/H96 -> 113.91855 | L96: =F96*$H$1851/H96 -> 6.5925086 | M96: =M95*((K96+(L96/12))/K95) -> 184.19859 | N96: =G96*$H$1851/H96 -> 10.635914 | O96: =N96*(M96/K96) -> 17.197554 | P96: NA | R96: NA | U96: =((J96/J97+J96/1200+((1+J97/1200)^(-119))*(1-J96/J97))) -> 1.0044058 | V96: =V95*U95*H95/H96 -> 2.1611187 | W96: =(($M216/$M96)^(1/10)-1) -> 0.10972464 | X96: =(($V216/$V96)^(1/10)-1) -> 0.051712284 | Y96: =W96-X96 -> 0.058012351
A97: 1878.04 | B97: =VALUE(LEFT(A97, 4)) -> 1878 | C97: 4 | D97: =DATE(B97, VALUE(C97), 1) -> 686018 | E97: 3.33 | F97: 0.1867 | G97: 0.3033 | H97: 8.8485091 | I97: =I96+1/12 -> 1878.2917 | J97: =J94*9/12+J106*3/12 -> 4.31 | K97: =E97*$H$1851/H97 -> 118.34217 | L97: =F97*$H$1851/H97 -> 6.6349801 | M97: =M96*((K97+(L97/12))/K96) -> 192.24532 | N97: =G97*$H$1851/H97 -> 10.778733 | O97: =N97*(M97/K97) -> 17.509912 | P97: NA | R97: NA | U97: =((J97/J98+J97/1200+((1+J98/1200)^(-119))*(1-J97/J98))) -> 1.0043978 | V97: =V96*U96*H96/H97 -> 2.1939853 | W97: =(($M217/$M97)^(1/10)-1) -> 0.10714224 | X97: =(($V217/$V97)^(1/10)-1) -> 0.051818823 | Y97: =W97-X97 -> 0.05532342
A98: 1878.05 | B98: =VALUE(LEFT(A98, 4)) -> 1878 | C98: 5 | D98: =DATE(B98, VALUE(C98), 1) -> 686048 | E98: 3.34 | F98: 0.1858 | G98: 0.3042 | H98: 8.5630942 | I98: =I97+1/12 -> 1878.375 | J98: =J94*8/12+J106*4/12 -> 4.3 | K98: =E98*$H$1851/H98 -> 122.65384 | L98: =F98*$H$1851/H98 -> 6.823079 | M98: =M97*((K98+(L98/12))/K97) -> 200.17324 | N98: =G98*$H$1851/H98 -> 11.171047 | O98: =N98*(M98/K98) -> 18.231347 | P98: NA | R98: NA | U98: =((J98/J99+J98/1200+((1+J99/1200)^(-119))*(1-J98/J99))) -> 1.0043899 | V98: =V97*U97*H97/H98 -> 2.277083 | W98: =(($M218/$M98)^(1/10)-1) -> 0.10590338 | X98: =(($V218/$V98)^(1/10)-1) -> 0.0496174 | Y98: =W98-X98 -> 0.056285983
A99: 1878.06 | B99: =VALUE(LEFT(A99, 4)) -> 1878 | C99: 6 | D99: =DATE(B99, VALUE(C99), 1) -> 686079 | E99: 3.41 | F99: 0.185 | G99: 0.305 | H99: 8.3728446 | I99: =I98+1/12 -> 1878.4583 | J99: =J94*7/12+J106*5/12 -> 4.29 | K99: =E99*$H$1851/H99 -> 128.06981 | L99: =F99*$H$1851/H99 -> 6.9480687 | M99: =M98*((K99+(L99/12))/K98) -> 209.95714 | N99: =G99*$H$1851/H99 -> 11.454924 | O99: =N99*(M99/K99) -> 18.779157 | P99: NA | R99: NA | U99: =((J99/J100+J99/1200+((1+J100/1200)^(-119))*(1-J99/J100))) -> 1.0043819 | V99: =V98*U98*H98/H99 -> 2.3390466 | W99: =(($M219/$M99)^(1/10)-1) -> 0.098920944 | X99: =(($V219/$V99)^(1/10)-1) -> 0.04851612 | Y99: =W99-X99 -> 0.050404823
A100: 1878.07 | B100: =VALUE(LEFT(A100, 4)) -> 1878 | C100: 7 | D100: =DATE(B100, VALUE(C100), 1) -> 686109 | E100: 3.48 | F100: 0.1842 | G100: 0.3058 | H100: 8.4679289 | I100: =I99+1/12 -> 1878.5417 | J100: =J94*6/12+J106*6/12 -> 4.28 | K100: =E100*$H$1851/H100 -> 129.23122 | L100: =F100*$H$1851/H100 -> 6.8403422 | M100: =M99*((K100+(L100/12))/K99) -> 212.79566 | N100: =G100*$H$1851/H100 -> 11.356008 | O100: =N100*(M100/K100) -> 18.699113 | P100: NA | R100: NA | U100: =((J100/J101+J100/1200+((1+J101/1200)^(-119))*(1-J100/J101))) -> 1.004374 | V100: =V99*U99*H99/H100 -> 2.3229165 | W100: =(($M220/$M100)^(1/10)-1) -> 0.099383618 | X100: =(($V220/$V100)^(1/10)-1) -> 0.048472789 | Y100: =W100-X100 -> 0.050910829
A101: 1878.08 | B101: =VALUE(LEFT(A101, 4)) -> 1878 | C101: 8 | D101: =DATE(B101, VALUE(C101), 1) -> 686140 | E101: 3.45 | F101: 0.1833 | G101: 0.3067 | H101: 8.5630942 | I101: =I100+1/12 -> 1878.625 | J101: =J94*5/12+J106*7/12 -> 4.27 | K101: =E101*$H$1851/H101 -> 126.69334 | L101: =F101*$H$1851/H101 -> 6.7312722 | M101: =M100*((K101+(L101/12))/K100) -> 209.54037 | N101: =G101*$H$1851/H101 -> 11.262854 | O101: =N101*(M101/K101) -> 18.627835 | P101: NA | R101: NA | U101: =((J101/J102+J101/1200+((1+J102/1200)^(-119))*(1-J101/J102))) -> 1.004366 | V101: =V100*U100*H100/H101 -> 2.3071484 | W101: =(($M221/$M101)^(1/10)-1) -> 0.1038276 | X101: =(($V221/$V101)^(1/10)-1) -> 0.049658128 | Y101: =W101-X101 -> 0.054169475
...

Sheet ICSA
A1: Link: | B1: Initial Claims (Number)
A3: Date | B3: ICSA
A4: 24473 | B4: 209000
A5: 24504 | B5: 229000
A6: 24532 | B6: 260750
A7: 24563 | B7: 263000
A8: 24593 | B8: 235750
A9: 24624 | B9: 232000
A10: 24654 | B10: 227800
A11: 24685 | B11: 212750
A12: 24716 | B12: 216400
A13: 24746 | B13: 216750
A14: 24777 | B14: 206250
A15: 24807 | B15: 211200
... A693: 45444 | B693: 236600

Sheet IURSA
A1: Link: | B1: Insured Unemployment Rate (%)
A3: Date | B3: IURSA
A4: 25934 | B4: 3.92
A5: 25965 | B5: 3.95
A6: 25993 | B6: 4.025
A7: 26024 | B7: 4.05
A8: 26054 | B8: 4.1
A9: 26085 | B9: 4.1
A10: 26115 | B10: 4.02
A11: 26146 | B11: 4.125
A12: 26177 | B12: 4.25
A13: 26207 | B13: 4.2
A14: 26238 | B14: 4.1
A15: 26268 | B15: 3.975
... A645: 45444 | B645: 1.2

Sheet JTSJOL
A1: Link: | B1: Job Openings: Total Nonfarm (Level in Thousands)
A3: Date | B3: JTSJOL
A4: 36861 | B4: 5088
A5: 36892 | B5: 5234
A6: 36923 | B6: 5097
A7: 36951 | B7: 4762
A8: 36982 | B8: 4615
A9: 37012 | B9: 4425
A10: 37043 | B10: 4361
A11: 37073 | B11: 4447
A12: 37104 | B12: 4024
A13: 37135 | B13: 4071
A14: 37165 | B14: 3707
A15: 37196 | B15: 3775
... A285: 45413 | B285: 8140

Sheet PAYEMS
A1: Link: | B1: All Employees, Total Nonfarm (Thousands of Persons)
A3: Date | B3: PAYEMS
A4: 14246 | B4: 29923
A5: 14277 | B5: 30100
A6: 14305 | B6: 30280
A7: 14336 | B7: 30094
A8: 14366 | B8: 30299
A9: 14397 | B9: 30502
A10: 14427 | B10: 30419
A11: 14458 | B11: 30663
A12: 14489 | B12: 31031
A13: 14519 | B13: 31411
A14: 14550 | B14: 31470
A15: 14580 | B15: 31542
... A1029: 45444 | B1029: 158638

Sheet MANEMP
A1: Link: | B1: All Employees, Manufacturing (Thousands of Persons)
A3: Date | B3: MANEMP
A4: 14246 | B4: 9077
A5: 14277 | B5: 9175
A6: 14305 | B6: 9275
A7: 14336 | B7: 9309
A8: 14366 | B8: 9299
A9: 14397 | B9: 9315
A10: 14427 | B10: 9231
A11: 14458 | B11: 9400
A12: 14489 | B12: 9604
A13: 14519 | B13: 9873
A14: 14550 | B14: 9896
A15: 14580 | B15: 9949
... A1029: 45444 | B1029: 12950

Sheet UNRATE
A1: Link: | B1: Unemployment Rate (%)
A3: Date | B3: UNRATE
A4: 17533 | B4: 3.4
A5: 17564 | B5: 3.8
A6: 17593 | B6: 4
A7: 17624 | B7: 3.9
A8: 17654 | B8: 3.5
A9: 17685 | B9: 3.6
A10: 17715 | B10: 3.6
A11: 17746 | B11: 3.9
A12: 17777 | B12: 3.8
A13: 17807 | B13: 3.7
A14: 17838 | B14: 3.8
A15: 17868 | B15: 4
... A921: 45444 | B921: 4.1

Sheet IEAXGS
A1: Link: | B1: Exports of goods and services (Millions of Dollars)
A3: Date | B3: IEAXGS
A4: 36161 | B4: 235387
A5: 36251 | B5: 238878
A6: 36342 | B6: 247493
A7: 36434 | B7: 254767
A8: 36526 | B8: 260656
A9: 36617 | B9: 269952
A10: 36708 | B10: 277204
A11: 36800 | B11: 275151
A12: 36892 | B12: 271148
A13: 36982 | B13: 262318
A14: 37073 | B14: 246592
A15: 37165 | B15: 235308
... A104: 45292 | B104: 787178

Sheet IEAMGSN
A1: Link: | B1: Imports of goods and services (Millions of Dollars)
A3: Date | B3: IEAMGSN
A4: 36161 | B4: 275721
A5: 36251 | B5: 300975
A6: 36342 | B6: 323481
A7: 36434 | B7: 332158
A8: 36526 | B8: 335244
A9: 36617 | B9: 359940
A10: 36708 | B10: 380471
A11: 36800 | B11: 376995
A12: 36892 | B12: 353790
A13: 36982 | B13: 350895
A14: 37073 | B14: 342129
A15: 37165 | B15: 328926
... A104: 45292 | B104: 948773

Sheet GFDEGDQ188S
A1: Link: | B1: Federal Debt: Total Public Debt as Percent of Gross Domestic Product (%)
A3: Date | B3: GFDEGDQ188S
A4: 24108 | B4: 40.33999
A5: 24198 | B5: 39.26763
A6: 24289 | B6: 39.62091
A7: 24381 | B7: 39.51977
A8: 24473 | B8: 39.20383
A9: 24563 | B9: 38.03292
A10: 24654 | B10: 38.82145
A11: 24746 | B11: 39.10231
A12: 24838 | B12: 38.42951
A13: 24929 | B13: 36.96379
A14: 25020 | B14: 37.30897
A15: 25112 | B15: 36.98532
... A236: 45292 | B236: 122.34717
